[
    {
        "dBZ": "-32",
        "black_and_white": "#00000000",
        "original": "#00000000",
        "universal_blue": "#00000000",
        "titan": "#00000000",
        "TWC": "#00000000",
        "meteored": "#00000000",
        "nextrad_lvl_iii": "#00000000",
        "rainbow_si": "#00000000",
        "dark_sky": "#00000000"
    },
    {
        "dBZ": "-31",
        "black_and_white": "#010101ff",
        "original": "#00000000",
        "universal_blue": "#00000000",
        "titan": "#00000000",
        "TWC": "#00000000",
        "meteored": "#00000000",
        "nextrad_lvl_iii": "#00000000",
        "rainbow_si": "#00000000",
        "dark_sky": "#00000000"
    },
    {
        "dBZ": "-30",
        "black_and_white": "#020202ff",
        "original": "#00000000",
        "universal_blue": "#00000000",
        "titan": "#00000000",
        "TWC": "#00000000",
        "meteored": "#00000000",
        "nextrad_lvl_iii": "#00000000",
        "rainbow_si": "#00000000",
        "dark_sky": "#00000000"
    },
    {
        "dBZ": "-29",
        "black_and_white": "#030303ff",
        "original": "#00000000",
        "universal_blue": "#00000000",
        "titan": "#00000000",
        "TWC": "#00000000",
        "meteored": "#00000000",
        "nextrad_lvl_iii": "#00000000",
        "rainbow_si": "#00000000",
        "dark_sky": "#00000000"
    },
    {
        "dBZ": "-28",
        "black_and_white": "#040404ff",
        "original": "#00000000",
        "universal_blue": "#00000000",
        "titan": "#00000000",
        "TWC": "#00000000",
        "meteored": "#00000000",
        "nextrad_lvl_iii": "#00000000",
        "rainbow_si": "#00000000",
        "dark_sky": "#00000000"
    },
    {
        "dBZ": "-27",
        "black_and_white": "#050505ff",
        "original": "#00000000",
        "universal_blue": "#00000000",
        "titan": "#00000000",
        "TWC": "#00000000",
        "meteored": "#00000000",
        "nextrad_lvl_iii": "#00000000",
        "rainbow_si": "#00000000",
        "dark_sky": "#00000000"
    },
    {
        "dBZ": "-26",
        "black_and_white": "#060606ff",
        "original": "#00000000",
        "universal_blue": "#00000000",
        "titan": "#00000000",
        "TWC": "#00000000",
        "meteored": "#00000000",
        "nextrad_lvl_iii": "#00000000",
        "rainbow_si": "#00000000",
        "dark_sky": "#00000000"
    },
    {
        "dBZ": "-25",
        "black_and_white": "#070707ff",
        "original": "#00000000",
        "universal_blue": "#00000000",
        "titan": "#00000000",
        "TWC": "#00000000",
        "meteored": "#00000000",
        "nextrad_lvl_iii": "#00000000",
        "rainbow_si": "#00000000",
        "dark_sky": "#00000000"
    },
    {
        "dBZ": "-24",
        "black_and_white": "#080808ff",
        "original": "#00000000",
        "universal_blue": "#00000000",
        "titan": "#00000000",
        "TWC": "#00000000",
        "meteored": "#00000000",
        "nextrad_lvl_iii": "#00000000",
        "rainbow_si": "#00000000",
        "dark_sky": "#00000000"
    },
    {
        "dBZ": "-23",
        "black_and_white": "#090909ff",
        "original": "#00000000",
        "universal_blue": "#00000000",
        "titan": "#00000000",
        "TWC": "#00000000",
        "meteored": "#00000000",
        "nextrad_lvl_iii": "#00000000",
        "rainbow_si": "#00000000",
        "dark_sky": "#00000000"
    },
    {
        "dBZ": "-22",
        "black_and_white": "#0a0a0aff",
        "original": "#00000000",
        "universal_blue": "#00000000",
        "titan": "#00000000",
        "TWC": "#00000000",
        "meteored": "#00000000",
        "nextrad_lvl_iii": "#00000000",
        "rainbow_si": "#00000000",
        "dark_sky": "#00000000"
    },
    {
        "dBZ": "-21",
        "black_and_white": "#0b0b0bff",
        "original": "#00000000",
        "universal_blue": "#00000000",
        "titan": "#00000000",
        "TWC": "#00000000",
        "meteored": "#00000000",
        "nextrad_lvl_iii": "#00000000",
        "rainbow_si": "#00000000",
        "dark_sky": "#00000000"
    },
    {
        "dBZ": "-20",
        "black_and_white": "#0c0c0cff",
        "original": "#00000000",
        "universal_blue": "#00000000",
        "titan": "#00000000",
        "TWC": "#00000000",
        "meteored": "#00000000",
        "nextrad_lvl_iii": "#00000000",
        "rainbow_si": "#00000000",
        "dark_sky": "#00000000"
    },
    {
        "dBZ": "-19",
        "black_and_white": "#0d0d0dff",
        "original": "#00000000",
        "universal_blue": "#00000000",
        "titan": "#00000000",
        "TWC": "#00000000",
        "meteored": "#00000000",
        "nextrad_lvl_iii": "#00000000",
        "rainbow_si": "#00000000",
        "dark_sky": "#00000000"
    },
    {
        "dBZ": "-18",
        "black_and_white": "#0e0e0eff",
        "original": "#00000000",
        "universal_blue": "#00000000",
        "titan": "#00000000",
        "TWC": "#00000000",
        "meteored": "#00000000",
        "nextrad_lvl_iii": "#00000000",
        "rainbow_si": "#00000000",
        "dark_sky": "#00000000"
    },
    {
        "dBZ": "-17",
        "black_and_white": "#0f0f0fff",
        "original": "#00000000",
        "universal_blue": "#00000000",
        "titan": "#00000000",
        "TWC": "#00000000",
        "meteored": "#00000000",
        "nextrad_lvl_iii": "#00000000",
        "rainbow_si": "#00000000",
        "dark_sky": "#00000000"
    },
    {
        "dBZ": "-16",
        "black_and_white": "#101010ff",
        "original": "#00000000",
        "universal_blue": "#00000000",
        "titan": "#00000000",
        "TWC": "#00000000",
        "meteored": "#00000000",
        "nextrad_lvl_iii": "#00000000",
        "rainbow_si": "#00000000",
        "dark_sky": "#00000000"
    },
    {
        "dBZ": "-15",
        "black_and_white": "#111111ff",
        "original": "#00000000",
        "universal_blue": "#00000000",
        "titan": "#00000000",
        "TWC": "#00000000",
        "meteored": "#00000000",
        "nextrad_lvl_iii": "#00000000",
        "rainbow_si": "#00000000",
        "dark_sky": "#00000000"
    },
    {
        "dBZ": "-14",
        "black_and_white": "#121212ff",
        "original": "#00000000",
        "universal_blue": "#00000000",
        "titan": "#00000000",
        "TWC": "#00000000",
        "meteored": "#00000000",
        "nextrad_lvl_iii": "#00000000",
        "rainbow_si": "#00000000",
        "dark_sky": "#00000000"
    },
    {
        "dBZ": "-13",
        "black_and_white": "#131313ff",
        "original": "#00000000",
        "universal_blue": "#00000000",
        "titan": "#00000000",
        "TWC": "#00000000",
        "meteored": "#00000000",
        "nextrad_lvl_iii": "#00000000",
        "rainbow_si": "#00000000",
        "dark_sky": "#00000000"
    },
    {
        "dBZ": "-12",
        "black_and_white": "#141414ff",
        "original": "#00000000",
        "universal_blue": "#00000000",
        "titan": "#00000000",
        "TWC": "#00000000",
        "meteored": "#00000000",
        "nextrad_lvl_iii": "#00000000",
        "rainbow_si": "#00000000",
        "dark_sky": "#00000000"
    },
    {
        "dBZ": "-11",
        "black_and_white": "#151515ff",
        "original": "#00000000",
        "universal_blue": "#00000000",
        "titan": "#00000000",
        "TWC": "#00000000",
        "meteored": "#00000000",
        "nextrad_lvl_iii": "#00000000",
        "rainbow_si": "#00000000",
        "dark_sky": "#00000000"
    },
    {
        "dBZ": "-10",
        "black_and_white": "#161616ff",
        "original": "#00000000",
        "universal_blue": "#63615911",
        "titan": "#353535ff",
        "TWC": "#00000000",
        "meteored": "#00000000",
        "nextrad_lvl_iii": "#00000000",
        "rainbow_si": "#00000000",
        "dark_sky": "#00000000"
    },
    {
        "dBZ": "-9",
        "black_and_white": "#171717ff",
        "original": "#00000000",
        "universal_blue": "#6361591b",
        "titan": "#353535ff",
        "TWC": "#00000000",
        "meteored": "#00000000",
        "nextrad_lvl_iii": "#00000000",
        "rainbow_si": "#00000000",
        "dark_sky": "#00000000"
    },
    {
        "dBZ": "-8",
        "black_and_white": "#181818ff",
        "original": "#00000000",
        "universal_blue": "#63615925",
        "titan": "#353535ff",
        "TWC": "#00000000",
        "meteored": "#00000000",
        "nextrad_lvl_iii": "#00000000",
        "rainbow_si": "#00000000",
        "dark_sky": "#00000000"
    },
    {
        "dBZ": "-7",
        "black_and_white": "#191919ff",
        "original": "#00000000",
        "universal_blue": "#6361592f",
        "titan": "#353535ff",
        "TWC": "#00000000",
        "meteored": "#00000000",
        "nextrad_lvl_iii": "#00000000",
        "rainbow_si": "#00000000",
        "dark_sky": "#00000000"
    },
    {
        "dBZ": "-6",
        "black_and_white": "#1a1a1aff",
        "original": "#00000000",
        "universal_blue": "#63615939",
        "titan": "#353535ff",
        "TWC": "#00000000",
        "meteored": "#00000000",
        "nextrad_lvl_iii": "#00000000",
        "rainbow_si": "#00000000",
        "dark_sky": "#00000000"
    },
    {
        "dBZ": "-5",
        "black_and_white": "#1b1b1bff",
        "original": "#00000000",
        "universal_blue": "#79746044",
        "titan": "#757575ff",
        "TWC": "#00000000",
        "meteored": "#00000000",
        "nextrad_lvl_iii": "#00000000",
        "rainbow_si": "#00000000",
        "dark_sky": "#00000000"
    },
    {
        "dBZ": "-4",
        "black_and_white": "#1c1c1cff",
        "original": "#00000000",
        "universal_blue": "#79746051",
        "titan": "#757575ff",
        "TWC": "#00000000",
        "meteored": "#00000000",
        "nextrad_lvl_iii": "#00000000",
        "rainbow_si": "#00000000",
        "dark_sky": "#00000000"
    },
    {
        "dBZ": "-3",
        "black_and_white": "#1d1d1dff",
        "original": "#00000000",
        "universal_blue": "#7974605f",
        "titan": "#757575ff",
        "TWC": "#00000000",
        "meteored": "#00000000",
        "nextrad_lvl_iii": "#00000000",
        "rainbow_si": "#00000000",
        "dark_sky": "#00000000"
    },
    {
        "dBZ": "-2",
        "black_and_white": "#1e1e1eff",
        "original": "#00000000",
        "universal_blue": "#7974606c",
        "titan": "#757575ff",
        "TWC": "#00000000",
        "meteored": "#00000000",
        "nextrad_lvl_iii": "#00000000",
        "rainbow_si": "#00000000",
        "dark_sky": "#00000000"
    },
    {
        "dBZ": "-1",
        "black_and_white": "#1f1f1fff",
        "original": "#00000000",
        "universal_blue": "#7974607a",
        "titan": "#757575ff",
        "TWC": "#00000000",
        "meteored": "#00000000",
        "nextrad_lvl_iii": "#00000000",
        "rainbow_si": "#00000000",
        "dark_sky": "#00000000"
    },
    {
        "dBZ": "0",
        "black_and_white": "#202020ff",
        "original": "#00000000",
        "universal_blue": "#92887188",
        "titan": "#005a00ff",
        "TWC": "#00000000",
        "meteored": "#00000000",
        "nextrad_lvl_iii": "#04e9e7ff",
        "rainbow_si": "#00000000",
        "dark_sky": "#005eb611"
    },
    {
        "dBZ": "1",
        "black_and_white": "#212121ff",
        "original": "#00000000",
        "universal_blue": "#92887195",
        "titan": "#005a00ff",
        "TWC": "#00000000",
        "meteored": "#00000000",
        "nextrad_lvl_iii": "#04e9e7ff",
        "rainbow_si": "#00000000",
        "dark_sky": "#005eb614"
    },
    {
        "dBZ": "2",
        "black_and_white": "#222222ff",
        "original": "#00000000",
        "universal_blue": "#928871a3",
        "titan": "#005a00ff",
        "TWC": "#00000000",
        "meteored": "#00000000",
        "nextrad_lvl_iii": "#04e9e7ff",
        "rainbow_si": "#00000000",
        "dark_sky": "#005eb617"
    },
    {
        "dBZ": "3",
        "black_and_white": "#232323ff",
        "original": "#00000000",
        "universal_blue": "#928871b0",
        "titan": "#005a00ff",
        "TWC": "#00000000",
        "meteored": "#00000000",
        "nextrad_lvl_iii": "#04e9e7ff",
        "rainbow_si": "#00000000",
        "dark_sky": "#005eb61b"
    },
    {
        "dBZ": "4",
        "black_and_white": "#242424ff",
        "original": "#00000000",
        "universal_blue": "#928871be",
        "titan": "#005a00ff",
        "TWC": "#00000000",
        "meteored": "#00000000",
        "nextrad_lvl_iii": "#04e9e7ff",
        "rainbow_si": "#00000000",
        "dark_sky": "#005eb61e"
    },
    {
        "dBZ": "5",
        "black_and_white": "#252525ff",
        "original": "#00000000",
        "universal_blue": "#cec087cc",
        "titan": "#007e00ff",
        "TWC": "#00000000",
        "meteored": "#00000000",
        "nextrad_lvl_iii": "#00efe7ff",
        "rainbow_si": "#00000000",
        "dark_sky": "#005eb622"
    },
    {
        "dBZ": "6",
        "black_and_white": "#262626ff",
        "original": "#00000000",
        "universal_blue": "#cec087d6",
        "titan": "#007e00ff",
        "TWC": "#00000000",
        "meteored": "#00000000",
        "nextrad_lvl_iii": "#00efe7ff",
        "rainbow_si": "#00000000",
        "dark_sky": "#005eb625"
    },
    {
        "dBZ": "7",
        "black_and_white": "#272727ff",
        "original": "#00000000",
        "universal_blue": "#cec087e0",
        "titan": "#007e00ff",
        "TWC": "#00000000",
        "meteored": "#00000000",
        "nextrad_lvl_iii": "#00efe7ff",
        "rainbow_si": "#00000000",
        "dark_sky": "#005eb628"
    },
    {
        "dBZ": "8",
        "black_and_white": "#282828ff",
        "original": "#00000000",
        "universal_blue": "#cec087ea",
        "titan": "#007e00ff",
        "TWC": "#00000000",
        "meteored": "#00000000",
        "nextrad_lvl_iii": "#00efe7ff",
        "rainbow_si": "#00000000",
        "dark_sky": "#005eb62c"
    },
    {
        "dBZ": "9",
        "black_and_white": "#292929ff",
        "original": "#00000000",
        "universal_blue": "#cec087f4",
        "titan": "#007e00ff",
        "TWC": "#00000000",
        "meteored": "#00000000",
        "nextrad_lvl_iii": "#00efe7ff",
        "rainbow_si": "#00000000",
        "dark_sky": "#005eb62f"
    },
    {
        "dBZ": "10",
        "black_and_white": "#2a2a2aff",
        "original": "#dfdfdfff",
        "universal_blue": "#88ddeeff",
        "titan": "#087fdbff",
        "TWC": "#01b714ff",
        "meteored": "#3ffefcff",
        "nextrad_lvl_iii": "#009cf7ff",
        "rainbow_si": "#009f9fff",
        "dark_sky": "#005eb633"
    },
    {
        "dBZ": "11",
        "black_and_white": "#2b2b2bff",
        "original": "#dfdfdfff",
        "universal_blue": "#88ddeeff",
        "titan": "#087fdbff",
        "TWC": "#01b614ff",
        "meteored": "#3ffefcff",
        "nextrad_lvl_iii": "#009cf7ff",
        "rainbow_si": "#009e9eff",
        "dark_sky": "#005eb639"
    },
    {
        "dBZ": "12",
        "black_and_white": "#2c2c2cff",
        "original": "#dfdfdfff",
        "universal_blue": "#88ddeeff",
        "titan": "#087fdbff",
        "TWC": "#01b414ff",
        "meteored": "#3ffefcff",
        "nextrad_lvl_iii": "#009cf7ff",
        "rainbow_si": "#009d99ff",
        "dark_sky": "#005eb640"
    },
    {
        "dBZ": "13",
        "black_and_white": "#2d2d2dff",
        "original": "#dfdfdfff",
        "universal_blue": "#88ddeeff",
        "titan": "#087fdbff",
        "TWC": "#02ad14ff",
        "meteored": "#3ffefcff",
        "nextrad_lvl_iii": "#009cf7ff",
        "rainbow_si": "#009a8cff",
        "dark_sky": "#005eb647"
    },
    {
        "dBZ": "14",
        "black_and_white": "#2e2e2eff",
        "original": "#dfdfdfff",
        "universal_blue": "#88ddeeff",
        "titan": "#087fdbff",
        "TWC": "#049f14ff",
        "meteored": "#3ffefcff",
        "nextrad_lvl_iii": "#009cf7ff",
        "rainbow_si": "#009573ff",
        "dark_sky": "#005eb64e"
    },
    {
        "dBZ": "15",
        "black_and_white": "#2f2f2fff",
        "original": "#9bea8fff",
        "universal_blue": "#0099ccff",
        "titan": "#1c47e8ff",
        "TWC": "#088915ff",
        "meteored": "#1790f9ff",
        "nextrad_lvl_iii": "#0000f7ff",
        "rainbow_si": "#008c4bff",
        "dark_sky": "#005eb655"
    },
    {
        "dBZ": "16",
        "black_and_white": "#303030ff",
        "original": "#9bea8fff",
        "universal_blue": "#0099ccff",
        "titan": "#1c47e8ff",
        "TWC": "#088815ff",
        "meteored": "#1790f9ff",
        "nextrad_lvl_iii": "#0000f7ff",
        "rainbow_si": "#008c4aff",
        "dark_sky": "#005eb662"
    },
    {
        "dBZ": "17",
        "black_and_white": "#313131ff",
        "original": "#9bea8fff",
        "universal_blue": "#0099ccff",
        "titan": "#1c47e8ff",
        "TWC": "#088615ff",
        "meteored": "#1790f9ff",
        "nextrad_lvl_iii": "#0000f7ff",
        "rainbow_si": "#009047ff",
        "dark_sky": "#005eb670"
    },
    {
        "dBZ": "18",
        "black_and_white": "#323232ff",
        "original": "#9bea8fff",
        "universal_blue": "#0099ccff",
        "titan": "#1c47e8ff",
        "TWC": "#098116ff",
        "meteored": "#1790f9ff",
        "nextrad_lvl_iii": "#0000f7ff",
        "rainbow_si": "#009b40ff",
        "dark_sky": "#005eb67d"
    },
    {
        "dBZ": "19",
        "black_and_white": "#333333ff",
        "original": "#9bea8fff",
        "universal_blue": "#0099ccff",
        "titan": "#1c47e8ff",
        "TWC": "#0c7617ff",
        "meteored": "#1790f9ff",
        "nextrad_lvl_iii": "#0000f7ff",
        "rainbow_si": "#00b031ff",
        "dark_sky": "#005eb68b"
    },
    {
        "dBZ": "20",
        "black_and_white": "#343434ff",
        "original": "#58ff42ff",
        "universal_blue": "#0077aaff",
        "titan": "#6e0dc6ff",
        "TWC": "#11651aff",
        "meteored": "#0000f3ff",
        "nextrad_lvl_iii": "#00ff00ff",
        "rainbow_si": "#00d319ff",
        "dark_sky": "#005eb699"
    },
    {
        "dBZ": "21",
        "black_and_white": "#353535ff",
        "original": "#58ff42ff",
        "universal_blue": "#0077aaff",
        "titan": "#6e0dc6ff",
        "TWC": "#106419ff",
        "meteored": "#0000f3ff",
        "nextrad_lvl_iii": "#00ff00ff",
        "rainbow_si": "#00d319ff",
        "dark_sky": "#075cb4a6"
    },
    {
        "dBZ": "22",
        "black_and_white": "#363636ff",
        "original": "#58ff42ff",
        "universal_blue": "#0077aaff",
        "titan": "#6e0dc6ff",
        "TWC": "#106218ff",
        "meteored": "#0000f3ff",
        "nextrad_lvl_iii": "#00ff00ff",
        "rainbow_si": "#02d519ff",
        "dark_sky": "#0e5bb3b4"
    },
    {
        "dBZ": "23",
        "black_and_white": "#373737ff",
        "original": "#58ff42ff",
        "universal_blue": "#0077aaff",
        "titan": "#6e0dc6ff",
        "TWC": "#0e5d15ff",
        "meteored": "#0000f3ff",
        "nextrad_lvl_iii": "#00ff00ff",
        "rainbow_si": "#07dc1aff",
        "dark_sky": "#155ab1c1"
    },
    {
        "dBZ": "24",
        "black_and_white": "#383838ff",
        "original": "#58ff42ff",
        "universal_blue": "#0077aaff",
        "titan": "#6e0dc6ff",
        "TWC": "#0b5310ff",
        "meteored": "#0000f3ff",
        "nextrad_lvl_iii": "#00ff00ff",
        "rainbow_si": "#10e81dff",
        "dark_sky": "#1c59b0cf"
    },
    {
        "dBZ": "25",
        "black_and_white": "#393939ff",
        "original": "#47c278ff",
        "universal_blue": "#005588ff",
        "titan": "#c80f86ff",
        "TWC": "#064307ff",
        "meteored": "#41ff50ff",
        "nextrad_lvl_iii": "#03b703ff",
        "rainbow_si": "#21fd22ff",
        "dark_sky": "#2458afdd"
    },
    {
        "dBZ": "26",
        "black_and_white": "#3a3a3aff",
        "original": "#47c278ff",
        "universal_blue": "#005588ff",
        "titan": "#c80f86ff",
        "TWC": "#074407ff",
        "meteored": "#41ff50ff",
        "nextrad_lvl_iii": "#03b703ff",
        "rainbow_si": "#22fd21ff",
        "dark_sky": "#3955abe3"
    },
    {
        "dBZ": "27",
        "black_and_white": "#3b3b3bff",
        "original": "#47c278ff",
        "universal_blue": "#005588ff",
        "titan": "#c80f86ff",
        "TWC": "#154d07ff",
        "meteored": "#41ff50ff",
        "nextrad_lvl_iii": "#03b703ff",
        "rainbow_si": "#2ffd21ff",
        "dark_sky": "#4e52a7ea"
    },
    {
        "dBZ": "28",
        "black_and_white": "#3c3c3cff",
        "original": "#47c278ff",
        "universal_blue": "#005588ff",
        "titan": "#c80f86ff",
        "TWC": "#3b6707ff",
        "meteored": "#41ff50ff",
        "nextrad_lvl_iii": "#03b703ff",
        "rainbow_si": "#50fd20ff",
        "dark_sky": "#6350a3f1"
    },
    {
        "dBZ": "29",
        "black_and_white": "#3d3d3dff",
        "original": "#47c278ff",
        "universal_blue": "#005588ff",
        "titan": "#c80f86ff",
        "TWC": "#859a07ff",
        "meteored": "#41ff50ff",
        "nextrad_lvl_iii": "#03b703ff",
        "rainbow_si": "#92fd1eff",
        "dark_sky": "#784d9ff8"
    },
    {
        "dBZ": "30",
        "black_and_white": "#3e3e3eff",
        "original": "#4793f9ff",
        "universal_blue": "#ffee00ff",
        "titan": "#c06487ff",
        "TWC": "#ffee07ff",
        "meteored": "#32c23dff",
        "nextrad_lvl_iii": "#087305ff",
        "rainbow_si": "#fffd1bff",
        "dark_sky": "#8e4b9bff"
    },
    {
        "dBZ": "31",
        "black_and_white": "#3f3f3fff",
        "original": "#4793f9ff",
        "universal_blue": "#ffee00ff",
        "titan": "#c06487ff",
        "TWC": "#feed07ff",
        "meteored": "#32c23dff",
        "nextrad_lvl_iii": "#087305ff",
        "rainbow_si": "#fffc1aff",
        "dark_sky": "#a44c92ff"
    },
    {
        "dBZ": "32",
        "black_and_white": "#404040ff",
        "original": "#4793f9ff",
        "universal_blue": "#ffee00ff",
        "titan": "#c06487ff",
        "TWC": "#feea07ff",
        "meteored": "#32c23dff",
        "nextrad_lvl_iii": "#087305ff",
        "rainbow_si": "#fffa19ff",
        "dark_sky": "#ba4e89ff"
    },
    {
        "dBZ": "33",
        "black_and_white": "#414141ff",
        "original": "#4793f9ff",
        "universal_blue": "#ffee00ff",
        "titan": "#c06487ff",
        "TWC": "#fde207ff",
        "meteored": "#32c23dff",
        "nextrad_lvl_iii": "#087305ff",
        "rainbow_si": "#fff415ff",
        "dark_sky": "#d04f81ff"
    },
    {
        "dBZ": "34",
        "black_and_white": "#424242ff",
        "original": "#4793f9ff",
        "universal_blue": "#ffee00ff",
        "titan": "#c06487ff",
        "TWC": "#fbd307ff",
        "meteored": "#32c23dff",
        "nextrad_lvl_iii": "#087305ff",
        "rainbow_si": "#ffe80dff",
        "dark_sky": "#e65178ff"
    },
    {
        "dBZ": "35",
        "black_and_white": "#434343ff",
        "original": "#0c59ffff",
        "universal_blue": "#ffaa00ff",
        "titan": "#d2883bff",
        "TWC": "#f8bb08ff",
        "meteored": "#4b8339ff",
        "nextrad_lvl_iii": "#ffff00ff",
        "rainbow_si": "#ffd400ff",
        "dark_sky": "#fc5370ff"
    },
    {
        "dBZ": "36",
        "black_and_white": "#444444ff",
        "original": "#0c59ffff",
        "universal_blue": "#ffaa00ff",
        "titan": "#d2883bff",
        "TWC": "#f7ba08ff",
        "meteored": "#4b8339ff",
        "nextrad_lvl_iii": "#ffff00ff",
        "rainbow_si": "#ffd300ff",
        "dark_sky": "#fc676fff"
    },
    {
        "dBZ": "37",
        "black_and_white": "#454545ff",
        "original": "#0c59ffff",
        "universal_blue": "#ffaa00ff",
        "titan": "#d2883bff",
        "TWC": "#f7b708ff",
        "meteored": "#4b8339ff",
        "nextrad_lvl_iii": "#ffff00ff",
        "rainbow_si": "#ffd100ff",
        "dark_sky": "#fd7b6fff"
    },
    {
        "dBZ": "38",
        "black_and_white": "#464646ff",
        "original": "#0c59ffff",
        "universal_blue": "#ffaa00ff",
        "titan": "#d2883bff",
        "TWC": "#f6b008ff",
        "meteored": "#4b8339ff",
        "nextrad_lvl_iii": "#ffff00ff",
        "rainbow_si": "#ffcb00ff",
        "dark_sky": "#fd8f6eff"
    },
    {
        "dBZ": "39",
        "black_and_white": "#474747ff",
        "original": "#0c59ffff",
        "universal_blue": "#ffaa00ff",
        "titan": "#d2883bff",
        "TWC": "#f5a208ff",
        "meteored": "#4b8339ff",
        "nextrad_lvl_iii": "#ffff00ff",
        "rainbow_si": "#ffbf00ff",
        "dark_sky": "#fea36eff"
    },
    {
        "dBZ": "40",
        "black_and_white": "#484848ff",
        "original": "#6153c1ff",
        "universal_blue": "#ff7700ff",
        "titan": "#fac431ff",
        "TWC": "#f38b08ff",
        "meteored": "#ffff50ff",
        "nextrad_lvl_iii": "#ecce00ff",
        "rainbow_si": "#ffab00ff",
        "dark_sky": "#ffb76eff"
    },
    {
        "dBZ": "41",
        "black_and_white": "#494949ff",
        "original": "#6153c1ff",
        "universal_blue": "#ff7700ff",
        "titan": "#fac431ff",
        "TWC": "#f28a08ff",
        "meteored": "#ffff50ff",
        "nextrad_lvl_iii": "#ecce00ff",
        "rainbow_si": "#ffaa00ff",
        "dark_sky": "#ffc559ff"
    },
    {
        "dBZ": "42",
        "black_and_white": "#4a4a4aff",
        "original": "#6153c1ff",
        "universal_blue": "#ff7700ff",
        "titan": "#fac431ff",
        "TWC": "#f28908ff",
        "meteored": "#ffff50ff",
        "nextrad_lvl_iii": "#ecce00ff",
        "rainbow_si": "#ffa700ff",
        "dark_sky": "#ffd344ff"
    },
    {
        "dBZ": "43",
        "black_and_white": "#4b4b4bff",
        "original": "#6153c1ff",
        "universal_blue": "#ff7700ff",
        "titan": "#fac431ff",
        "TWC": "#f28508ff",
        "meteored": "#ffff50ff",
        "nextrad_lvl_iii": "#ecce00ff",
        "rainbow_si": "#ff9d00ff",
        "dark_sky": "#ffe12eff"
    },
    {
        "dBZ": "44",
        "black_and_white": "#4c4c4cff",
        "original": "#6153c1ff",
        "universal_blue": "#ff7700ff",
        "titan": "#fac431ff",
        "TWC": "#f17d08ff",
        "meteored": "#ffff50ff",
        "nextrad_lvl_iii": "#ecce00ff",
        "rainbow_si": "#ff8b00ff",
        "dark_sky": "#ffef19ff"
    },
    {
        "dBZ": "45",
        "black_and_white": "#4d4d4dff",
        "original": "#ff93a3ff",
        "universal_blue": "#ff4400ff",
        "titan": "#fefb02ff",
        "TWC": "#f07108ff",
        "meteored": "#fdbb3cff",
        "nextrad_lvl_iii": "#fe9300ff",
        "rainbow_si": "#ff6e00ff",
        "dark_sky": "#fffd05ff"
    },
    {
        "dBZ": "46",
        "black_and_white": "#4e4e4eff",
        "original": "#ff93a3ff",
        "universal_blue": "#ff4400ff",
        "titan": "#fefb02ff",
        "TWC": "#ef7008ff",
        "meteored": "#fdbb3cff",
        "nextrad_lvl_iii": "#fe9300ff",
        "rainbow_si": "#fe6d00ff",
        "dark_sky": "#fffd05ff"
    },
    {
        "dBZ": "47",
        "black_and_white": "#4f4f4fff",
        "original": "#ff93a3ff",
        "universal_blue": "#ff4400ff",
        "titan": "#fefb02ff",
        "TWC": "#ef6f08ff",
        "meteored": "#fdbb3cff",
        "nextrad_lvl_iii": "#fe9300ff",
        "rainbow_si": "#fe6700ff",
        "dark_sky": "#fffd05ff"
    },
    {
        "dBZ": "48",
        "black_and_white": "#505050ff",
        "original": "#ff93a3ff",
        "universal_blue": "#ff4400ff",
        "titan": "#fefb02ff",
        "TWC": "#ee6c08ff",
        "meteored": "#fdbb3cff",
        "nextrad_lvl_iii": "#fe9300ff",
        "rainbow_si": "#fb5900ff",
        "dark_sky": "#fffd05ff"
    },
    {
        "dBZ": "49",
        "black_and_white": "#515151ff",
        "original": "#ff93a3ff",
        "universal_blue": "#ff4400ff",
        "titan": "#fefb02ff",
        "TWC": "#ec6708ff",
        "meteored": "#fdbb3cff",
        "nextrad_lvl_iii": "#fe9300ff",
        "rainbow_si": "#f73d01ff",
        "dark_sky": "#fffd05ff"
    },
    {
        "dBZ": "50",
        "black_and_white": "#525252ff",
        "original": "#ff3f35ff",
        "universal_blue": "#ee0000ff",
        "titan": "#fe9a58ff",
        "TWC": "#ea5e09ff",
        "meteored": "#df5e0bff",
        "nextrad_lvl_iii": "#ff0000ff",
        "rainbow_si": "#f01002ff",
        "dark_sky": "#fffd05ff"
    },
    {
        "dBZ": "51",
        "black_and_white": "#535353ff",
        "original": "#ff3f35ff",
        "universal_blue": "#ee0000ff",
        "titan": "#fe9a58ff",
        "TWC": "#e95d09ff",
        "meteored": "#df5e0bff",
        "nextrad_lvl_iii": "#ff0000ff",
        "rainbow_si": "#ef0f02ff",
        "dark_sky": "#fffd05ff"
    },
    {
        "dBZ": "52",
        "black_and_white": "#545454ff",
        "original": "#ff3f35ff",
        "universal_blue": "#ee0000ff",
        "titan": "#fe9a58ff",
        "TWC": "#e95b09ff",
        "meteored": "#df5e0bff",
        "nextrad_lvl_iii": "#ff0000ff",
        "rainbow_si": "#ed0f04ff",
        "dark_sky": "#fffd05ff"
    },
    {
        "dBZ": "53",
        "black_and_white": "#555555ff",
        "original": "#ff3f35ff",
        "universal_blue": "#ee0000ff",
        "titan": "#fe9a58ff",
        "TWC": "#e75509ff",
        "meteored": "#df5e0bff",
        "nextrad_lvl_iii": "#ff0000ff",
        "rainbow_si": "#e90d09ff",
        "dark_sky": "#fffd05ff"
    },
    {
        "dBZ": "54",
        "black_and_white": "#565656ff",
        "original": "#ff3f35ff",
        "universal_blue": "#ee0000ff",
        "titan": "#fe9a58ff",
        "TWC": "#e44a09ff",
        "meteored": "#df5e0bff",
        "nextrad_lvl_iii": "#ff0000ff",
        "rainbow_si": "#df0a12ff",
        "dark_sky": "#fffd05ff"
    },
    {
        "dBZ": "55",
        "black_and_white": "#575757ff",
        "original": "#c20511ff",
        "universal_blue": "#990000ff",
        "titan": "#fe5f05ff",
        "TWC": "#df370aff",
        "meteored": "#fd8788ff",
        "nextrad_lvl_iii": "#bd0000ff",
        "rainbow_si": "#d00523ff",
        "dark_sky": "#fffd05ff"
    },
    {
        "dBZ": "56",
        "black_and_white": "#585858ff",
        "original": "#c20511ff",
        "universal_blue": "#990000ff",
        "titan": "#fe5f05ff",
        "TWC": "#de360aff",
        "meteored": "#fd8788ff",
        "nextrad_lvl_iii": "#bd0000ff",
        "rainbow_si": "#d00424ff",
        "dark_sky": "#fffd05ff"
    },
    {
        "dBZ": "57",
        "black_and_white": "#595959ff",
        "original": "#c20511ff",
        "universal_blue": "#990000ff",
        "titan": "#fe5f05ff",
        "TWC": "#de340aff",
        "meteored": "#fd8788ff",
        "nextrad_lvl_iii": "#bd0000ff",
        "rainbow_si": "#d1042cff",
        "dark_sky": "#fffd05ff"
    },
    {
        "dBZ": "58",
        "black_and_white": "#5a5a5aff",
        "original": "#c20511ff",
        "universal_blue": "#990000ff",
        "titan": "#fe5f05ff",
        "TWC": "#dc2e0aff",
        "meteored": "#fd8788ff",
        "nextrad_lvl_iii": "#bd0000ff",
        "rainbow_si": "#d40341ff",
        "dark_sky": "#fffd05ff"
    },
    {
        "dBZ": "59",
        "black_and_white": "#5b5b5bff",
        "original": "#c20511ff",
        "universal_blue": "#990000ff",
        "titan": "#fe5f05ff",
        "TWC": "#d8230bff",
        "meteored": "#fd8788ff",
        "nextrad_lvl_iii": "#bd0000ff",
        "rainbow_si": "#da026bff",
        "dark_sky": "#fffd05ff"
    },
    {
        "dBZ": "60",
        "black_and_white": "#5c5c5cff",
        "original": "#ffeb0aff",
        "universal_blue": "#ffaaffff",
        "titan": "#fd341cff",
        "TWC": "#d3100cff",
        "meteored": "#e90000ff",
        "nextrad_lvl_iii": "#bd0000ff",
        "rainbow_si": "#e400b1ff",
        "dark_sky": "#fffd05ff"
    },
    {
        "dBZ": "61",
        "black_and_white": "#5d5d5dff",
        "original": "#ffeb0aff",
        "universal_blue": "#ffaaffff",
        "titan": "#fd341cff",
        "TWC": "#d20f0bff",
        "meteored": "#e90000ff",
        "nextrad_lvl_iii": "#bd0000ff",
        "rainbow_si": "#e400b1ff",
        "dark_sky": "#fffd05ff"
    },
    {
        "dBZ": "62",
        "black_and_white": "#5e5e5eff",
        "original": "#ffeb0aff",
        "universal_blue": "#ffaaffff",
        "titan": "#fd341cff",
        "TWC": "#d10f0bff",
        "meteored": "#e90000ff",
        "nextrad_lvl_iii": "#bd0000ff",
        "rainbow_si": "#e503b5ff",
        "dark_sky": "#fffd05ff"
    },
    {
        "dBZ": "63",
        "black_and_white": "#5f5f5fff",
        "original": "#ffeb0aff",
        "universal_blue": "#ffaaffff",
        "titan": "#fd341cff",
        "TWC": "#ce0f0bff",
        "meteored": "#e90000ff",
        "nextrad_lvl_iii": "#bd0000ff",
        "rainbow_si": "#e90bc1ff",
        "dark_sky": "#fffd05ff"
    },
    {
        "dBZ": "64",
        "black_and_white": "#606060ff",
        "original": "#ffeb0aff",
        "universal_blue": "#ffaaffff",
        "titan": "#fd341cff",
        "TWC": "#c90e0aff",
        "meteored": "#e90000ff",
        "nextrad_lvl_iii": "#bd0000ff",
        "rainbow_si": "#f11ad8ff",
        "dark_sky": "#fffd05ff"
    },
    {
        "dBZ": "65",
        "black_and_white": "#616161ff",
        "original": "#ff9811ff",
        "universal_blue": "#ff77ffff",
        "titan": "#bebebeff",
        "TWC": "#c00d09ff",
        "meteored": "#a80000ff",
        "nextrad_lvl_iii": "#fe00feff",
        "rainbow_si": "#ff33ffff",
        "dark_sky": "#fffd05ff"
    },
    {
        "dBZ": "66",
        "black_and_white": "#626262ff",
        "original": "#ff9811ff",
        "universal_blue": "#ff77ffff",
        "titan": "#bebebeff",
        "TWC": "#bf0c08ff",
        "meteored": "#a80000ff",
        "nextrad_lvl_iii": "#fe00feff",
        "rainbow_si": "#ff33ffff",
        "dark_sky": "#fffd05ff"
    },
    {
        "dBZ": "67",
        "black_and_white": "#636363ff",
        "original": "#ff9811ff",
        "universal_blue": "#ff77ffff",
        "titan": "#bebebeff",
        "TWC": "#bf0c08ff",
        "meteored": "#a80000ff",
        "nextrad_lvl_iii": "#fe00feff",
        "rainbow_si": "#ff36ffff",
        "dark_sky": "#fffd05ff"
    },
    {
        "dBZ": "68",
        "black_and_white": "#646464ff",
        "original": "#ff9811ff",
        "universal_blue": "#ff77ffff",
        "titan": "#bebebeff",
        "TWC": "#be0c08ff",
        "meteored": "#a80000ff",
        "nextrad_lvl_iii": "#fe00feff",
        "rainbow_si": "#ff3effff",
        "dark_sky": "#fffd05ff"
    },
    {
        "dBZ": "69",
        "black_and_white": "#656565ff",
        "original": "#ff9811ff",
        "universal_blue": "#ff77ffff",
        "titan": "#bebebeff",
        "TWC": "#bb0c08ff",
        "meteored": "#a80000ff",
        "nextrad_lvl_iii": "#fe00feff",
        "rainbow_si": "#ff4dffff",
        "dark_sky": "#fffd05ff"
    },
    {
        "dBZ": "70",
        "black_and_white": "#666666ff",
        "original": "#a84c06ff",
        "universal_blue": "#ff44ffff",
        "titan": "#d3d3d3ff",
        "TWC": "#b80c08ff",
        "meteored": "#ef5beeff",
        "nextrad_lvl_iii": "#9c52c6ff",
        "rainbow_si": "#ff66ffff",
        "dark_sky": "#fffd05ff"
    },
    {
        "dBZ": "71",
        "black_and_white": "#676767ff",
        "original": "#a84c06ff",
        "universal_blue": "#ff44ffff",
        "titan": "#d3d3d3ff",
        "TWC": "#b80c08ff",
        "meteored": "#ef5beeff",
        "nextrad_lvl_iii": "#9c52c6ff",
        "rainbow_si": "#ff66ffff",
        "dark_sky": "#fffd05ff"
    },
    {
        "dBZ": "72",
        "black_and_white": "#686868ff",
        "original": "#a84c06ff",
        "universal_blue": "#ff44ffff",
        "titan": "#d3d3d3ff",
        "TWC": "#b80c08ff",
        "meteored": "#ef5beeff",
        "nextrad_lvl_iii": "#9c52c6ff",
        "rainbow_si": "#ff69ffff",
        "dark_sky": "#fffd05ff"
    },
    {
        "dBZ": "73",
        "black_and_white": "#696969ff",
        "original": "#a84c06ff",
        "universal_blue": "#ff44ffff",
        "titan": "#d3d3d3ff",
        "TWC": "#b80c08ff",
        "meteored": "#ef5beeff",
        "nextrad_lvl_iii": "#9c52c6ff",
        "rainbow_si": "#ff71ffff",
        "dark_sky": "#fffd05ff"
    },
    {
        "dBZ": "74",
        "black_and_white": "#6a6a6aff",
        "original": "#a84c06ff",
        "universal_blue": "#ff44ffff",
        "titan": "#d3d3d3ff",
        "TWC": "#b80c08ff",
        "meteored": "#ef5beeff",
        "nextrad_lvl_iii": "#9c52c6ff",
        "rainbow_si": "#ff80ffff",
        "dark_sky": "#fffd05ff"
    },
    {
        "dBZ": "75",
        "black_and_white": "#6b6b6bff",
        "original": "#dda8ffff",
        "universal_blue": "#ff00ffff",
        "titan": "#d3d3d3ff",
        "TWC": "#b80c08ff",
        "meteored": "#924cbeff",
        "nextrad_lvl_iii": "#fefefeff",
        "rainbow_si": "#ff99ffff",
        "dark_sky": "#fffd05ff"
    },
    {
        "dBZ": "76",
        "black_and_white": "#6c6c6cff",
        "original": "#dda8ffff",
        "universal_blue": "#ff00ffff",
        "titan": "#d3d3d3ff",
        "TWC": "#b80c08ff",
        "meteored": "#924cbeff",
        "nextrad_lvl_iii": "#fefefeff",
        "rainbow_si": "#ff99ffff",
        "dark_sky": "#fffd05ff"
    },
    {
        "dBZ": "77",
        "black_and_white": "#6d6d6dff",
        "original": "#dda8ffff",
        "universal_blue": "#ff00ffff",
        "titan": "#d3d3d3ff",
        "TWC": "#b80c08ff",
        "meteored": "#924cbeff",
        "nextrad_lvl_iii": "#fefefeff",
        "rainbow_si": "#ff9affff",
        "dark_sky": "#fffd05ff"
    },
    {
        "dBZ": "78",
        "black_and_white": "#6e6e6eff",
        "original": "#dda8ffff",
        "universal_blue": "#ff00ffff",
        "titan": "#d3d3d3ff",
        "TWC": "#b80c08ff",
        "meteored": "#924cbeff",
        "nextrad_lvl_iii": "#fefefeff",
        "rainbow_si": "#ff9cffff",
        "dark_sky": "#fffd05ff"
    },
    {
        "dBZ": "79",
        "black_and_white": "#6f6f6fff",
        "original": "#dda8ffff",
        "universal_blue": "#ff00ffff",
        "titan": "#d3d3d3ff",
        "TWC": "#b80c08ff",
        "meteored": "#924cbeff",
        "nextrad_lvl_iii": "#fefefeff",
        "rainbow_si": "#ffa1ffff",
        "dark_sky": "#fffd05ff"
    },
    {
        "dBZ": "80",
        "black_and_white": "#707070ff",
        "original": "#ffffffff",
        "universal_blue": "#aa00aaff",
        "titan": "#d3d3d3ff",
        "TWC": "#b80c08ff",
        "meteored": "#502a68ff",
        "nextrad_lvl_iii": "#ffffffff",
        "rainbow_si": "#ffaaffff",
        "dark_sky": "#fffd05ff"
    },
    {
        "dBZ": "81",
        "black_and_white": "#717171ff",
        "original": "#ffffffff",
        "universal_blue": "#aa00aaff",
        "titan": "#d3d3d3ff",
        "TWC": "#b80c08ff",
        "meteored": "#502a68ff",
        "nextrad_lvl_iii": "#ffffffff",
        "rainbow_si": "#ffaaffff",
        "dark_sky": "#fffd05ff"
    },
    {
        "dBZ": "82",
        "black_and_white": "#727272ff",
        "original": "#ffffffff",
        "universal_blue": "#aa00aaff",
        "titan": "#d3d3d3ff",
        "TWC": "#b80c08ff",
        "meteored": "#502a68ff",
        "nextrad_lvl_iii": "#ffffffff",
        "rainbow_si": "#ffaaffff",
        "dark_sky": "#fffd05ff"
    },
    {
        "dBZ": "83",
        "black_and_white": "#737373ff",
        "original": "#ffffffff",
        "universal_blue": "#aa00aaff",
        "titan": "#d3d3d3ff",
        "TWC": "#b80c08ff",
        "meteored": "#502a68ff",
        "nextrad_lvl_iii": "#ffffffff",
        "rainbow_si": "#ffaaffff",
        "dark_sky": "#fffd05ff"
    },
    {
        "dBZ": "84",
        "black_and_white": "#747474ff",
        "original": "#ffffffff",
        "universal_blue": "#aa00aaff",
        "titan": "#d3d3d3ff",
        "TWC": "#b80c08ff",
        "meteored": "#502a68ff",
        "nextrad_lvl_iii": "#ffffffff",
        "rainbow_si": "#ffaaffff",
        "dark_sky": "#fffd05ff"
    },
    {
        "dBZ": "85",
        "black_and_white": "#757575ff",
        "original": "#ffffffff",
        "universal_blue": "#aa00aaff",
        "titan": "#d3d3d3ff",
        "TWC": "#b80c08ff",
        "meteored": "#502a68ff",
        "nextrad_lvl_iii": "#ffffffff",
        "rainbow_si": "#ffaaffff",
        "dark_sky": "#fffd05ff"
    },
    {
        "dBZ": "86",
        "black_and_white": "#767676ff",
        "original": "#ffffffff",
        "universal_blue": "#aa00aaff",
        "titan": "#d3d3d3ff",
        "TWC": "#b80c08ff",
        "meteored": "#502a68ff",
        "nextrad_lvl_iii": "#ffffffff",
        "rainbow_si": "#ffaaffff",
        "dark_sky": "#fffd05ff"
    },
    {
        "dBZ": "87",
        "black_and_white": "#777777ff",
        "original": "#ffffffff",
        "universal_blue": "#aa00aaff",
        "titan": "#d3d3d3ff",
        "TWC": "#b80c08ff",
        "meteored": "#502a68ff",
        "nextrad_lvl_iii": "#ffffffff",
        "rainbow_si": "#ffaaffff",
        "dark_sky": "#fffd05ff"
    },
    {
        "dBZ": "88",
        "black_and_white": "#787878ff",
        "original": "#ffffffff",
        "universal_blue": "#aa00aaff",
        "titan": "#d3d3d3ff",
        "TWC": "#b80c08ff",
        "meteored": "#502a68ff",
        "nextrad_lvl_iii": "#ffffffff",
        "rainbow_si": "#ffaaffff",
        "dark_sky": "#fffd05ff"
    },
    {
        "dBZ": "89",
        "black_and_white": "#797979ff",
        "original": "#ffffffff",
        "universal_blue": "#aa00aaff",
        "titan": "#d3d3d3ff",
        "TWC": "#b80c08ff",
        "meteored": "#502a68ff",
        "nextrad_lvl_iii": "#ffffffff",
        "rainbow_si": "#ffaaffff",
        "dark_sky": "#fffd05ff"
    },
    {
        "dBZ": "90",
        "black_and_white": "#7a7a7aff",
        "original": "#ffffffff",
        "universal_blue": "#aa00aaff",
        "titan": "#d3d3d3ff",
        "TWC": "#b80c08ff",
        "meteored": "#502a68ff",
        "nextrad_lvl_iii": "#ffffffff",
        "rainbow_si": "#ffaaffff",
        "dark_sky": "#fffd05ff"
    },
    {
        "dBZ": "91",
        "black_and_white": "#7b7b7bff",
        "original": "#ffffffff",
        "universal_blue": "#aa00aaff",
        "titan": "#d3d3d3ff",
        "TWC": "#b80c08ff",
        "meteored": "#502a68ff",
        "nextrad_lvl_iii": "#ffffffff",
        "rainbow_si": "#ffaaffff",
        "dark_sky": "#fffd05ff"
    },
    {
        "dBZ": "92",
        "black_and_white": "#7c7c7cff",
        "original": "#ffffffff",
        "universal_blue": "#aa00aaff",
        "titan": "#d3d3d3ff",
        "TWC": "#b80c08ff",
        "meteored": "#502a68ff",
        "nextrad_lvl_iii": "#ffffffff",
        "rainbow_si": "#ffaaffff",
        "dark_sky": "#fffd05ff"
    },
    {
        "dBZ": "93",
        "black_and_white": "#7d7d7dff",
        "original": "#ffffffff",
        "universal_blue": "#aa00aaff",
        "titan": "#d3d3d3ff",
        "TWC": "#b80c08ff",
        "meteored": "#502a68ff",
        "nextrad_lvl_iii": "#ffffffff",
        "rainbow_si": "#ffaaffff",
        "dark_sky": "#fffd05ff"
    },
    {
        "dBZ": "94",
        "black_and_white": "#7e7e7eff",
        "original": "#ffffffff",
        "universal_blue": "#aa00aaff",
        "titan": "#d3d3d3ff",
        "TWC": "#b80c08ff",
        "meteored": "#502a68ff",
        "nextrad_lvl_iii": "#ffffffff",
        "rainbow_si": "#ffaaffff",
        "dark_sky": "#fffd05ff"
    },
    {
        "dBZ": "95",
        "black_and_white": "#7f7f7fff",
        "original": "#ffffffff",
        "universal_blue": "#aa00aaff",
        "titan": "#d3d3d3ff",
        "TWC": "#b80c08ff",
        "meteored": "#502a68ff",
        "nextrad_lvl_iii": "#ffffffff",
        "rainbow_si": "#ffaaffff",
        "dark_sky": "#fffd05ff"
    },
    {
        "dBZ": "-32",
        "black_and_white": "#808080ff",
        "original": "#00000000",
        "universal_blue": "#00000000",
        "titan": "#00000000",
        "TWC": "#00000000",
        "meteored": "#00000000",
        "nextrad_lvl_iii": "#00000000",
        "rainbow_si": "#00000000",
        "dark_sky": "#00000000"
    },
    {
        "dBZ": "-31",
        "black_and_white": "#818181ff",
        "original": "#00000000",
        "universal_blue": "#00000000",
        "titan": "#00000000",
        "TWC": "#00000000",
        "meteored": "#00000000",
        "nextrad_lvl_iii": "#00000000",
        "rainbow_si": "#00000000",
        "dark_sky": "#00000000"
    },
    {
        "dBZ": "-30",
        "black_and_white": "#828282ff",
        "original": "#00000000",
        "universal_blue": "#00000000",
        "titan": "#00000000",
        "TWC": "#00000000",
        "meteored": "#00000000",
        "nextrad_lvl_iii": "#00000000",
        "rainbow_si": "#00000000",
        "dark_sky": "#00000000"
    },
    {
        "dBZ": "-29",
        "black_and_white": "#838383ff",
        "original": "#00000000",
        "universal_blue": "#00000000",
        "titan": "#00000000",
        "TWC": "#00000000",
        "meteored": "#00000000",
        "nextrad_lvl_iii": "#00000000",
        "rainbow_si": "#00000000",
        "dark_sky": "#00000000"
    },
    {
        "dBZ": "-28",
        "black_and_white": "#848484ff",
        "original": "#00000000",
        "universal_blue": "#00000000",
        "titan": "#00000000",
        "TWC": "#00000000",
        "meteored": "#00000000",
        "nextrad_lvl_iii": "#00000000",
        "rainbow_si": "#00000000",
        "dark_sky": "#00000000"
    },
    {
        "dBZ": "-27",
        "black_and_white": "#858585ff",
        "original": "#00000000",
        "universal_blue": "#00000000",
        "titan": "#00000000",
        "TWC": "#00000000",
        "meteored": "#00000000",
        "nextrad_lvl_iii": "#00000000",
        "rainbow_si": "#00000000",
        "dark_sky": "#00000000"
    },
    {
        "dBZ": "-26",
        "black_and_white": "#868686ff",
        "original": "#00000000",
        "universal_blue": "#00000000",
        "titan": "#00000000",
        "TWC": "#00000000",
        "meteored": "#00000000",
        "nextrad_lvl_iii": "#00000000",
        "rainbow_si": "#00000000",
        "dark_sky": "#00000000"
    },
    {
        "dBZ": "-25",
        "black_and_white": "#878787ff",
        "original": "#00000000",
        "universal_blue": "#00000000",
        "titan": "#00000000",
        "TWC": "#00000000",
        "meteored": "#00000000",
        "nextrad_lvl_iii": "#00000000",
        "rainbow_si": "#00000000",
        "dark_sky": "#00000000"
    },
    {
        "dBZ": "-24",
        "black_and_white": "#888888ff",
        "original": "#00000000",
        "universal_blue": "#00000000",
        "titan": "#00000000",
        "TWC": "#00000000",
        "meteored": "#00000000",
        "nextrad_lvl_iii": "#00000000",
        "rainbow_si": "#00000000",
        "dark_sky": "#00000000"
    },
    {
        "dBZ": "-23",
        "black_and_white": "#898989ff",
        "original": "#00000000",
        "universal_blue": "#00000000",
        "titan": "#00000000",
        "TWC": "#00000000",
        "meteored": "#00000000",
        "nextrad_lvl_iii": "#00000000",
        "rainbow_si": "#00000000",
        "dark_sky": "#00000000"
    },
    {
        "dBZ": "-22",
        "black_and_white": "#8a8a8aff",
        "original": "#00000000",
        "universal_blue": "#00000000",
        "titan": "#00000000",
        "TWC": "#00000000",
        "meteored": "#00000000",
        "nextrad_lvl_iii": "#00000000",
        "rainbow_si": "#00000000",
        "dark_sky": "#00000000"
    },
    {
        "dBZ": "-21",
        "black_and_white": "#8b8b8bff",
        "original": "#00000000",
        "universal_blue": "#00000000",
        "titan": "#00000000",
        "TWC": "#00000000",
        "meteored": "#00000000",
        "nextrad_lvl_iii": "#00000000",
        "rainbow_si": "#00000000",
        "dark_sky": "#00000000"
    },
    {
        "dBZ": "-20",
        "black_and_white": "#8c8c8cff",
        "original": "#efffffff",
        "universal_blue": "#efffffff",
        "titan": "#efffffff",
        "TWC": "#efffffff",
        "meteored": "#00000000",
        "nextrad_lvl_iii": "#00000000",
        "rainbow_si": "#efffffff",
        "dark_sky": "#efffffff"
    },
    {
        "dBZ": "-19",
        "black_and_white": "#8d8d8dff",
        "original": "#efffffff",
        "universal_blue": "#efffffff",
        "titan": "#efffffff",
        "TWC": "#eeffffff",
        "meteored": "#00000000",
        "nextrad_lvl_iii": "#00000000",
        "rainbow_si": "#eeffffff",
        "dark_sky": "#ebffffff"
    },
    {
        "dBZ": "-18",
        "black_and_white": "#8e8e8eff",
        "original": "#efffffff",
        "universal_blue": "#efffffff",
        "titan": "#efffffff",
        "TWC": "#edffffff",
        "meteored": "#00000000",
        "nextrad_lvl_iii": "#00000000",
        "rainbow_si": "#edffffff",
        "dark_sky": "#e8ffffff"
    },
    {
        "dBZ": "-17",
        "black_and_white": "#8f8f8fff",
        "original": "#efffffff",
        "universal_blue": "#efffffff",
        "titan": "#efffffff",
        "TWC": "#ebffffff",
        "meteored": "#00000000",
        "nextrad_lvl_iii": "#00000000",
        "rainbow_si": "#ebffffff",
        "dark_sky": "#e5ffffff"
    },
    {
        "dBZ": "-16",
        "black_and_white": "#909090ff",
        "original": "#efffffff",
        "universal_blue": "#efffffff",
        "titan": "#efffffff",
        "TWC": "#e6ffffff",
        "meteored": "#00000000",
        "nextrad_lvl_iii": "#00000000",
        "rainbow_si": "#e6ffffff",
        "dark_sky": "#e2ffffff"
    },
    {
        "dBZ": "-15",
        "black_and_white": "#919191ff",
        "original": "#dfffffff",
        "universal_blue": "#dfffffff",
        "titan": "#dfffffff",
        "TWC": "#dfffffff",
        "meteored": "#00000000",
        "nextrad_lvl_iii": "#00000000",
        "rainbow_si": "#dfffffff",
        "dark_sky": "#dfffffff"
    },
    {
        "dBZ": "-14",
        "black_and_white": "#929292ff",
        "original": "#dfffffff",
        "universal_blue": "#dfffffff",
        "titan": "#dfffffff",
        "TWC": "#deffffff",
        "meteored": "#00000000",
        "nextrad_lvl_iii": "#00000000",
        "rainbow_si": "#deffffff",
        "dark_sky": "#dbffffff"
    },
    {
        "dBZ": "-13",
        "black_and_white": "#939393ff",
        "original": "#dfffffff",
        "universal_blue": "#dfffffff",
        "titan": "#dfffffff",
        "TWC": "#ddffffff",
        "meteored": "#00000000",
        "nextrad_lvl_iii": "#00000000",
        "rainbow_si": "#ddffffff",
        "dark_sky": "#d8ffffff"
    },
    {
        "dBZ": "-12",
        "black_and_white": "#949494ff",
        "original": "#dfffffff",
        "universal_blue": "#dfffffff",
        "titan": "#dfffffff",
        "TWC": "#dbffffff",
        "meteored": "#00000000",
        "nextrad_lvl_iii": "#00000000",
        "rainbow_si": "#dbffffff",
        "dark_sky": "#d5ffffff"
    },
    {
        "dBZ": "-11",
        "black_and_white": "#959595ff",
        "original": "#dfffffff",
        "universal_blue": "#dfffffff",
        "titan": "#dfffffff",
        "TWC": "#d6ffffff",
        "meteored": "#00000000",
        "nextrad_lvl_iii": "#00000000",
        "rainbow_si": "#d6ffffff",
        "dark_sky": "#d2ffffff"
    },
    {
        "dBZ": "-10",
        "black_and_white": "#969696ff",
        "original": "#cfffffff",
        "universal_blue": "#cfffffff",
        "titan": "#cfffffff",
        "TWC": "#cfffffff",
        "meteored": "#00000000",
        "nextrad_lvl_iii": "#00000000",
        "rainbow_si": "#cfffffff",
        "dark_sky": "#cfffffff"
    },
    {
        "dBZ": "-9",
        "black_and_white": "#979797ff",
        "original": "#cfffffff",
        "universal_blue": "#cfffffff",
        "titan": "#cfffffff",
        "TWC": "#ceffffff",
        "meteored": "#00000000",
        "nextrad_lvl_iii": "#00000000",
        "rainbow_si": "#ceffffff",
        "dark_sky": "#cbffffff"
    },
    {
        "dBZ": "-8",
        "black_and_white": "#989898ff",
        "original": "#cfffffff",
        "universal_blue": "#cfffffff",
        "titan": "#cfffffff",
        "TWC": "#cdffffff",
        "meteored": "#00000000",
        "nextrad_lvl_iii": "#00000000",
        "rainbow_si": "#cdffffff",
        "dark_sky": "#c8ffffff"
    },
    {
        "dBZ": "-7",
        "black_and_white": "#999999ff",
        "original": "#cfffffff",
        "universal_blue": "#cfffffff",
        "titan": "#cfffffff",
        "TWC": "#cbffffff",
        "meteored": "#00000000",
        "nextrad_lvl_iii": "#00000000",
        "rainbow_si": "#cbffffff",
        "dark_sky": "#c5ffffff"
    },
    {
        "dBZ": "-6",
        "black_and_white": "#9a9a9aff",
        "original": "#cfffffff",
        "universal_blue": "#cfffffff",
        "titan": "#cfffffff",
        "TWC": "#c6ffffff",
        "meteored": "#00000000",
        "nextrad_lvl_iii": "#00000000",
        "rainbow_si": "#c6ffffff",
        "dark_sky": "#c2ffffff"
    },
    {
        "dBZ": "-5",
        "black_and_white": "#9b9b9bff",
        "original": "#bfffffff",
        "universal_blue": "#bfffffff",
        "titan": "#bfffffff",
        "TWC": "#bfffffff",
        "meteored": "#00000000",
        "nextrad_lvl_iii": "#00000000",
        "rainbow_si": "#bfffffff",
        "dark_sky": "#bfffffff"
    },
    {
        "dBZ": "-4",
        "black_and_white": "#9c9c9cff",
        "original": "#bfffffff",
        "universal_blue": "#bfffffff",
        "titan": "#bfffffff",
        "TWC": "#beffffff",
        "meteored": "#00000000",
        "nextrad_lvl_iii": "#00000000",
        "rainbow_si": "#beffffff",
        "dark_sky": "#bbffffff"
    },
    {
        "dBZ": "-3",
        "black_and_white": "#9d9d9dff",
        "original": "#bfffffff",
        "universal_blue": "#bfffffff",
        "titan": "#bfffffff",
        "TWC": "#bdffffff",
        "meteored": "#00000000",
        "nextrad_lvl_iii": "#00000000",
        "rainbow_si": "#bdffffff",
        "dark_sky": "#b8ffffff"
    },
    {
        "dBZ": "-2",
        "black_and_white": "#9e9e9eff",
        "original": "#bfffffff",
        "universal_blue": "#bfffffff",
        "titan": "#bfffffff",
        "TWC": "#bbffffff",
        "meteored": "#00000000",
        "nextrad_lvl_iii": "#00000000",
        "rainbow_si": "#bbffffff",
        "dark_sky": "#b5ffffff"
    },
    {
        "dBZ": "-1",
        "black_and_white": "#9f9f9fff",
        "original": "#bfffffff",
        "universal_blue": "#bfffffff",
        "titan": "#bfffffff",
        "TWC": "#b6ffffff",
        "meteored": "#00000000",
        "nextrad_lvl_iii": "#00000000",
        "rainbow_si": "#b6ffffff",
        "dark_sky": "#b2ffffff"
    },
    {
        "dBZ": "0",
        "black_and_white": "#a0a0a0ff",
        "original": "#afffffff",
        "universal_blue": "#afffffff",
        "titan": "#afffffff",
        "TWC": "#afffffff",
        "meteored": "#00000000",
        "nextrad_lvl_iii": "#00000000",
        "rainbow_si": "#afffffff",
        "dark_sky": "#afffffff"
    },
    {
        "dBZ": "1",
        "black_and_white": "#a1a1a1ff",
        "original": "#afffffff",
        "universal_blue": "#afffffff",
        "titan": "#afffffff",
        "TWC": "#aeffffff",
        "meteored": "#00000000",
        "nextrad_lvl_iii": "#00000000",
        "rainbow_si": "#aeffffff",
        "dark_sky": "#abffffff"
    },
    {
        "dBZ": "2",
        "black_and_white": "#a2a2a2ff",
        "original": "#afffffff",
        "universal_blue": "#afffffff",
        "titan": "#afffffff",
        "TWC": "#adffffff",
        "meteored": "#00000000",
        "nextrad_lvl_iii": "#00000000",
        "rainbow_si": "#adffffff",
        "dark_sky": "#a8ffffff"
    },
    {
        "dBZ": "3",
        "black_and_white": "#a3a3a3ff",
        "original": "#afffffff",
        "universal_blue": "#afffffff",
        "titan": "#afffffff",
        "TWC": "#abffffff",
        "meteored": "#00000000",
        "nextrad_lvl_iii": "#00000000",
        "rainbow_si": "#abffffff",
        "dark_sky": "#a5ffffff"
    },
    {
        "dBZ": "4",
        "black_and_white": "#a4a4a4ff",
        "original": "#afffffff",
        "universal_blue": "#afffffff",
        "titan": "#afffffff",
        "TWC": "#a6ffffff",
        "meteored": "#00000000",
        "nextrad_lvl_iii": "#00000000",
        "rainbow_si": "#a6ffffff",
        "dark_sky": "#a2ffffff"
    },
    {
        "dBZ": "5",
        "black_and_white": "#a5a5a5ff",
        "original": "#9fffffff",
        "universal_blue": "#9fffffff",
        "titan": "#9fffffff",
        "TWC": "#9fffffff",
        "meteored": "#00000000",
        "nextrad_lvl_iii": "#e5fefeff",
        "rainbow_si": "#9fffffff",
        "dark_sky": "#9fffffff"
    },
    {
        "dBZ": "6",
        "black_and_white": "#a6a6a6ff",
        "original": "#9fffffff",
        "universal_blue": "#9fffffff",
        "titan": "#9fffffff",
        "TWC": "#9effffff",
        "meteored": "#00000000",
        "nextrad_lvl_iii": "#e5fefeff",
        "rainbow_si": "#9effffff",
        "dark_sky": "#9bffffff"
    },
    {
        "dBZ": "7",
        "black_and_white": "#a7a7a7ff",
        "original": "#9fffffff",
        "universal_blue": "#9fffffff",
        "titan": "#9fffffff",
        "TWC": "#9dffffff",
        "meteored": "#00000000",
        "nextrad_lvl_iii": "#e5fefeff",
        "rainbow_si": "#9dffffff",
        "dark_sky": "#98ffffff"
    },
    {
        "dBZ": "8",
        "black_and_white": "#a8a8a8ff",
        "original": "#9fffffff",
        "universal_blue": "#9fffffff",
        "titan": "#9fffffff",
        "TWC": "#9bffffff",
        "meteored": "#00000000",
        "nextrad_lvl_iii": "#e5fefeff",
        "rainbow_si": "#9bffffff",
        "dark_sky": "#95ffffff"
    },
    {
        "dBZ": "9",
        "black_and_white": "#a9a9a9ff",
        "original": "#9fffffff",
        "universal_blue": "#9fffffff",
        "titan": "#9fffffff",
        "TWC": "#96ffffff",
        "meteored": "#00000000",
        "nextrad_lvl_iii": "#e5fefeff",
        "rainbow_si": "#96ffffff",
        "dark_sky": "#92ffffff"
    },
    {
        "dBZ": "10",
        "black_and_white": "#aaaaaaff",
        "original": "#8fffffff",
        "universal_blue": "#bfffffff",
        "titan": "#8fffffff",
        "TWC": "#8fffffff",
        "meteored": "#3ffefcff",
        "nextrad_lvl_iii": "#a3f3ffff",
        "rainbow_si": "#8fffffff",
        "dark_sky": "#8fffffff"
    },
    {
        "dBZ": "11",
        "black_and_white": "#abababff",
        "original": "#8fffffff",
        "universal_blue": "#bfffffff",
        "titan": "#8fffffff",
        "TWC": "#8efeffff",
        "meteored": "#3ffefcff",
        "nextrad_lvl_iii": "#a3f3ffff",
        "rainbow_si": "#8efeffff",
        "dark_sky": "#8bfbffff"
    },
    {
        "dBZ": "12",
        "black_and_white": "#acacacff",
        "original": "#8fffffff",
        "universal_blue": "#bfffffff",
        "titan": "#8fffffff",
        "TWC": "#8dfdffff",
        "meteored": "#3ffefcff",
        "nextrad_lvl_iii": "#a3f3ffff",
        "rainbow_si": "#8dfdffff",
        "dark_sky": "#88f8ffff"
    },
    {
        "dBZ": "13",
        "black_and_white": "#adadadff",
        "original": "#8fffffff",
        "universal_blue": "#bfffffff",
        "titan": "#8fffffff",
        "TWC": "#8bfbffff",
        "meteored": "#3ffefcff",
        "nextrad_lvl_iii": "#a3f3ffff",
        "rainbow_si": "#8bfbffff",
        "dark_sky": "#85f5ffff"
    },
    {
        "dBZ": "14",
        "black_and_white": "#aeaeaeff",
        "original": "#8fffffff",
        "universal_blue": "#bfffffff",
        "titan": "#8fffffff",
        "TWC": "#86f6ffff",
        "meteored": "#3ffefcff",
        "nextrad_lvl_iii": "#a3f3ffff",
        "rainbow_si": "#86f6ffff",
        "dark_sky": "#82f2ffff"
    },
    {
        "dBZ": "15",
        "black_and_white": "#afafafff",
        "original": "#7fefffff",
        "universal_blue": "#9fdfffff",
        "titan": "#7fefffff",
        "TWC": "#7fefffff",
        "meteored": "#1790f9ff",
        "nextrad_lvl_iii": "#51cffdff",
        "rainbow_si": "#7fefffff",
        "dark_sky": "#7fefffff"
    },
    {
        "dBZ": "16",
        "black_and_white": "#b0b0b0ff",
        "original": "#7fefffff",
        "universal_blue": "#9fdfffff",
        "titan": "#7fefffff",
        "TWC": "#7eeeffff",
        "meteored": "#1790f9ff",
        "nextrad_lvl_iii": "#51cffdff",
        "rainbow_si": "#7eeeffff",
        "dark_sky": "#7bebffff"
    },
    {
        "dBZ": "17",
        "black_and_white": "#b1b1b1ff",
        "original": "#7fefffff",
        "universal_blue": "#9fdfffff",
        "titan": "#7fefffff",
        "TWC": "#7dedffff",
        "meteored": "#1790f9ff",
        "nextrad_lvl_iii": "#51cffdff",
        "rainbow_si": "#7dedffff",
        "dark_sky": "#78e8ffff"
    },
    {
        "dBZ": "18",
        "black_and_white": "#b2b2b2ff",
        "original": "#7fefffff",
        "universal_blue": "#9fdfffff",
        "titan": "#7fefffff",
        "TWC": "#7bebffff",
        "meteored": "#1790f9ff",
        "nextrad_lvl_iii": "#51cffdff",
        "rainbow_si": "#7bebffff",
        "dark_sky": "#75e5ffff"
    },
    {
        "dBZ": "19",
        "black_and_white": "#b3b3b3ff",
        "original": "#7fefffff",
        "universal_blue": "#9fdfffff",
        "titan": "#7fefffff",
        "TWC": "#76e6ffff",
        "meteored": "#1790f9ff",
        "nextrad_lvl_iii": "#51cffdff",
        "rainbow_si": "#76e6ffff",
        "dark_sky": "#72e2ffff"
    },
    {
        "dBZ": "20",
        "black_and_white": "#b4b4b4ff",
        "original": "#6fdfffff",
        "universal_blue": "#7fbfffff",
        "titan": "#6fdfffff",
        "TWC": "#6fdfffff",
        "meteored": "#0000f3ff",
        "nextrad_lvl_iii": "#0d99fcff",
        "rainbow_si": "#6fdfffff",
        "dark_sky": "#6fdfffff"
    },
    {
        "dBZ": "21",
        "black_and_white": "#b5b5b5ff",
        "original": "#6fdfffff",
        "universal_blue": "#7fbfffff",
        "titan": "#6fdfffff",
        "TWC": "#6edeffff",
        "meteored": "#0000f3ff",
        "nextrad_lvl_iii": "#0d99fcff",
        "rainbow_si": "#6edeffff",
        "dark_sky": "#6bdbffff"
    },
    {
        "dBZ": "22",
        "black_and_white": "#b6b6b6ff",
        "original": "#6fdfffff",
        "universal_blue": "#7fbfffff",
        "titan": "#6fdfffff",
        "TWC": "#6dddffff",
        "meteored": "#0000f3ff",
        "nextrad_lvl_iii": "#0d99fcff",
        "rainbow_si": "#6dddffff",
        "dark_sky": "#68d8ffff"
    },
    {
        "dBZ": "23",
        "black_and_white": "#b7b7b7ff",
        "original": "#6fdfffff",
        "universal_blue": "#7fbfffff",
        "titan": "#6fdfffff",
        "TWC": "#6bdbffff",
        "meteored": "#0000f3ff",
        "nextrad_lvl_iii": "#0d99fcff",
        "rainbow_si": "#6bdbffff",
        "dark_sky": "#65d5ffff"
    },
    {
        "dBZ": "24",
        "black_and_white": "#b8b8b8ff",
        "original": "#6fdfffff",
        "universal_blue": "#7fbfffff",
        "titan": "#6fdfffff",
        "TWC": "#66d6ffff",
        "meteored": "#0000f3ff",
        "nextrad_lvl_iii": "#0d99fcff",
        "rainbow_si": "#66d6ffff",
        "dark_sky": "#62d2ffff"
    },
    {
        "dBZ": "25",
        "black_and_white": "#b9b9b9ff",
        "original": "#5fcfffff",
        "universal_blue": "#5f9fffff",
        "titan": "#5fcfffff",
        "TWC": "#5fcfffff",
        "meteored": "#41ff50ff",
        "nextrad_lvl_iii": "#0f75fbff",
        "rainbow_si": "#5fcfffff",
        "dark_sky": "#5fcfffff"
    },
    {
        "dBZ": "26",
        "black_and_white": "#bababaff",
        "original": "#5fcfffff",
        "universal_blue": "#5f9fffff",
        "titan": "#5fcfffff",
        "TWC": "#5eceffff",
        "meteored": "#41ff50ff",
        "nextrad_lvl_iii": "#0f75fbff",
        "rainbow_si": "#5eceffff",
        "dark_sky": "#5bc8ffff"
    },
    {
        "dBZ": "27",
        "black_and_white": "#bbbbbbff",
        "original": "#5fcfffff",
        "universal_blue": "#5f9fffff",
        "titan": "#5fcfffff",
        "TWC": "#5dccffff",
        "meteored": "#41ff50ff",
        "nextrad_lvl_iii": "#0f75fbff",
        "rainbow_si": "#5dccffff",
        "dark_sky": "#58c2ffff"
    },
    {
        "dBZ": "28",
        "black_and_white": "#bcbcbcff",
        "original": "#5fcfffff",
        "universal_blue": "#5f9fffff",
        "titan": "#5fcfffff",
        "TWC": "#5bc8ffff",
        "meteored": "#41ff50ff",
        "nextrad_lvl_iii": "#0f75fbff",
        "rainbow_si": "#5bc8ffff",
        "dark_sky": "#55bbffff"
    },
    {
        "dBZ": "29",
        "black_and_white": "#bdbdbdff",
        "original": "#5fcfffff",
        "universal_blue": "#5f9fffff",
        "titan": "#5fcfffff",
        "TWC": "#56beffff",
        "meteored": "#41ff50ff",
        "nextrad_lvl_iii": "#0f75fbff",
        "rainbow_si": "#56beffff",
        "dark_sky": "#52b5ffff"
    },
    {
        "dBZ": "30",
        "black_and_white": "#bebebeff",
        "original": "#4fafffff",
        "universal_blue": "#4f8fffff",
        "titan": "#4fafffff",
        "TWC": "#4fafffff",
        "meteored": "#32c23dff",
        "nextrad_lvl_iii": "#1053fbff",
        "rainbow_si": "#4fafffff",
        "dark_sky": "#4fafffff"
    },
    {
        "dBZ": "31",
        "black_and_white": "#bfbfbfff",
        "original": "#4fafffff",
        "universal_blue": "#4f8fffff",
        "titan": "#4fafffff",
        "TWC": "#4eaeffff",
        "meteored": "#32c23dff",
        "nextrad_lvl_iii": "#1053fbff",
        "rainbow_si": "#4eaeffff",
        "dark_sky": "#4babffff"
    },
    {
        "dBZ": "32",
        "black_and_white": "#c0c0c0ff",
        "original": "#4fafffff",
        "universal_blue": "#4f8fffff",
        "titan": "#4fafffff",
        "TWC": "#4dadffff",
        "meteored": "#32c23dff",
        "nextrad_lvl_iii": "#1053fbff",
        "rainbow_si": "#4dadffff",
        "dark_sky": "#48a8ffff"
    },
    {
        "dBZ": "33",
        "black_and_white": "#c1c1c1ff",
        "original": "#4fafffff",
        "universal_blue": "#4f8fffff",
        "titan": "#4fafffff",
        "TWC": "#4babffff",
        "meteored": "#32c23dff",
        "nextrad_lvl_iii": "#1053fbff",
        "rainbow_si": "#4babffff",
        "dark_sky": "#45a5ffff"
    },
    {
        "dBZ": "34",
        "black_and_white": "#c2c2c2ff",
        "original": "#4fafffff",
        "universal_blue": "#4f8fffff",
        "titan": "#4fafffff",
        "TWC": "#46a6ffff",
        "meteored": "#32c23dff",
        "nextrad_lvl_iii": "#1053fbff",
        "rainbow_si": "#46a6ffff",
        "dark_sky": "#42a2ffff"
    },
    {
        "dBZ": "35",
        "black_and_white": "#c3c3c3ff",
        "original": "#3f9fffff",
        "universal_blue": "#3f7fffff",
        "titan": "#3f9fffff",
        "TWC": "#3f9fffff",
        "meteored": "#4b8339ff",
        "nextrad_lvl_iii": "#103ffbff",
        "rainbow_si": "#3f9fffff",
        "dark_sky": "#3f9fffff"
    },
    {
        "dBZ": "36",
        "black_and_white": "#c4c4c4ff",
        "original": "#3f9fffff",
        "universal_blue": "#3f7fffff",
        "titan": "#3f9fffff",
        "TWC": "#3e9effff",
        "meteored": "#4b8339ff",
        "nextrad_lvl_iii": "#103ffbff",
        "rainbow_si": "#3e9effff",
        "dark_sky": "#3b9bffff"
    },
    {
        "dBZ": "37",
        "black_and_white": "#c5c5c5ff",
        "original": "#3f9fffff",
        "universal_blue": "#3f7fffff",
        "titan": "#3f9fffff",
        "TWC": "#3d9dffff",
        "meteored": "#4b8339ff",
        "nextrad_lvl_iii": "#103ffbff",
        "rainbow_si": "#3d9dffff",
        "dark_sky": "#3898ffff"
    },
    {
        "dBZ": "38",
        "black_and_white": "#c6c6c6ff",
        "original": "#3f9fffff",
        "universal_blue": "#3f7fffff",
        "titan": "#3f9fffff",
        "TWC": "#3b9bffff",
        "meteored": "#4b8339ff",
        "nextrad_lvl_iii": "#103ffbff",
        "rainbow_si": "#3b9bffff",
        "dark_sky": "#3595ffff"
    },
    {
        "dBZ": "39",
        "black_and_white": "#c7c7c7ff",
        "original": "#3f9fffff",
        "universal_blue": "#3f7fffff",
        "titan": "#3f9fffff",
        "TWC": "#3696ffff",
        "meteored": "#4b8339ff",
        "nextrad_lvl_iii": "#103ffbff",
        "rainbow_si": "#3696ffff",
        "dark_sky": "#3292ffff"
    },
    {
        "dBZ": "40",
        "black_and_white": "#c8c8c8ff",
        "original": "#2f8fffff",
        "universal_blue": "#2f6fffff",
        "titan": "#2f8fffff",
        "TWC": "#2f8fffff",
        "meteored": "#ffff50ff",
        "nextrad_lvl_iii": "#0b32cfff",
        "rainbow_si": "#2f8fffff",
        "dark_sky": "#2f8fffff"
    },
    {
        "dBZ": "41",
        "black_and_white": "#c9c9c9ff",
        "original": "#2f8fffff",
        "universal_blue": "#2f6fffff",
        "titan": "#2f8fffff",
        "TWC": "#2e8effff",
        "meteored": "#ffff50ff",
        "nextrad_lvl_iii": "#0b32cfff",
        "rainbow_si": "#2e8effff",
        "dark_sky": "#2b8bffff"
    },
    {
        "dBZ": "42",
        "black_and_white": "#cacacaff",
        "original": "#2f8fffff",
        "universal_blue": "#2f6fffff",
        "titan": "#2f8fffff",
        "TWC": "#2d8dffff",
        "meteored": "#ffff50ff",
        "nextrad_lvl_iii": "#0b32cfff",
        "rainbow_si": "#2d8dffff",
        "dark_sky": "#2888ffff"
    },
    {
        "dBZ": "43",
        "black_and_white": "#cbcbcbff",
        "original": "#2f8fffff",
        "universal_blue": "#2f6fffff",
        "titan": "#2f8fffff",
        "TWC": "#2b8bffff",
        "meteored": "#ffff50ff",
        "nextrad_lvl_iii": "#0b32cfff",
        "rainbow_si": "#2b8bffff",
        "dark_sky": "#2585ffff"
    },
    {
        "dBZ": "44",
        "black_and_white": "#ccccccff",
        "original": "#2f8fffff",
        "universal_blue": "#2f6fffff",
        "titan": "#2f8fffff",
        "TWC": "#2686ffff",
        "meteored": "#ffff50ff",
        "nextrad_lvl_iii": "#0b32cfff",
        "rainbow_si": "#2686ffff",
        "dark_sky": "#2282ffff"
    },
    {
        "dBZ": "45",
        "black_and_white": "#cdcdcdff",
        "original": "#1f7fffff",
        "universal_blue": "#1f5fffff",
        "titan": "#1f7fffff",
        "TWC": "#1f7fffff",
        "meteored": "#fdbb3cff",
        "nextrad_lvl_iii": "#0b32cfff",
        "rainbow_si": "#1f7fffff",
        "dark_sky": "#1f7fffff"
    },
    {
        "dBZ": "46",
        "black_and_white": "#cececeff",
        "original": "#1f7fffff",
        "universal_blue": "#1f5fffff",
        "titan": "#1f7fffff",
        "TWC": "#1e7effff",
        "meteored": "#fdbb3cff",
        "nextrad_lvl_iii": "#0b32cfff",
        "rainbow_si": "#1e7effff",
        "dark_sky": "#1b7bffff"
    },
    {
        "dBZ": "47",
        "black_and_white": "#cfcfcfff",
        "original": "#1f7fffff",
        "universal_blue": "#1f5fffff",
        "titan": "#1f7fffff",
        "TWC": "#1d7dffff",
        "meteored": "#fdbb3cff",
        "nextrad_lvl_iii": "#0b32cfff",
        "rainbow_si": "#1d7dffff",
        "dark_sky": "#1878ffff"
    },
    {
        "dBZ": "48",
        "black_and_white": "#d0d0d0ff",
        "original": "#1f7fffff",
        "universal_blue": "#1f5fffff",
        "titan": "#1f7fffff",
        "TWC": "#1b7bffff",
        "meteored": "#fdbb3cff",
        "nextrad_lvl_iii": "#0b32cfff",
        "rainbow_si": "#1b7bffff",
        "dark_sky": "#1575ffff"
    },
    {
        "dBZ": "49",
        "black_and_white": "#d1d1d1ff",
        "original": "#1f7fffff",
        "universal_blue": "#1f5fffff",
        "titan": "#1f7fffff",
        "TWC": "#1676ffff",
        "meteored": "#fdbb3cff",
        "nextrad_lvl_iii": "#0b32cfff",
        "rainbow_si": "#1676ffff",
        "dark_sky": "#1272ffff"
    },
    {
        "dBZ": "50",
        "black_and_white": "#d2d2d2ff",
        "original": "#0f6fffff",
        "universal_blue": "#0f4fffff",
        "titan": "#0f6fffff",
        "TWC": "#0f6fffff",
        "meteored": "#df5e0bff",
        "nextrad_lvl_iii": "#0726a4ff",
        "rainbow_si": "#0f6fffff",
        "dark_sky": "#0f6fffff"
    },
    {
        "dBZ": "51",
        "black_and_white": "#d3d3d3ff",
        "original": "#0f6fffff",
        "universal_blue": "#0f4fffff",
        "titan": "#0f6fffff",
        "TWC": "#0e6effff",
        "meteored": "#df5e0bff",
        "nextrad_lvl_iii": "#0726a4ff",
        "rainbow_si": "#0e6effff",
        "dark_sky": "#0c6bffff"
    },
    {
        "dBZ": "52",
        "black_and_white": "#d4d4d4ff",
        "original": "#0f6fffff",
        "universal_blue": "#0f4fffff",
        "titan": "#0f6fffff",
        "TWC": "#0e6dffff",
        "meteored": "#df5e0bff",
        "nextrad_lvl_iii": "#0726a4ff",
        "rainbow_si": "#0e6dffff",
        "dark_sky": "#0968ffff"
    },
    {
        "dBZ": "53",
        "black_and_white": "#d5d5d5ff",
        "original": "#0f6fffff",
        "universal_blue": "#0f4fffff",
        "titan": "#0f6fffff",
        "TWC": "#0b6bffff",
        "meteored": "#df5e0bff",
        "nextrad_lvl_iii": "#0726a4ff",
        "rainbow_si": "#0b6bffff",
        "dark_sky": "#0565ffff"
    },
    {
        "dBZ": "54",
        "black_and_white": "#d6d6d6ff",
        "original": "#0f6fffff",
        "universal_blue": "#0f4fffff",
        "titan": "#0f6fffff",
        "TWC": "#0766ffff",
        "meteored": "#df5e0bff",
        "nextrad_lvl_iii": "#0726a4ff",
        "rainbow_si": "#0766ffff",
        "dark_sky": "#0262ffff"
    },
    {
        "dBZ": "55",
        "black_and_white": "#d7d7d7ff",
        "original": "#005fffff",
        "universal_blue": "#003fffff",
        "titan": "#005fffff",
        "TWC": "#005fffff",
        "meteored": "#fd8788ff",
        "nextrad_lvl_iii": "#0726a4ff",
        "rainbow_si": "#005fffff",
        "dark_sky": "#005fffff"
    },
    {
        "dBZ": "56",
        "black_and_white": "#d8d8d8ff",
        "original": "#005fffff",
        "universal_blue": "#003fffff",
        "titan": "#005fffff",
        "TWC": "#005effff",
        "meteored": "#fd8788ff",
        "nextrad_lvl_iii": "#0726a4ff",
        "rainbow_si": "#005effff",
        "dark_sky": "#005bffff"
    },
    {
        "dBZ": "57",
        "black_and_white": "#d9d9d9ff",
        "original": "#005fffff",
        "universal_blue": "#003fffff",
        "titan": "#005fffff",
        "TWC": "#005dffff",
        "meteored": "#fd8788ff",
        "nextrad_lvl_iii": "#0726a4ff",
        "rainbow_si": "#005dffff",
        "dark_sky": "#0058ffff"
    },
    {
        "dBZ": "58",
        "black_and_white": "#dadadaff",
        "original": "#005fffff",
        "universal_blue": "#003fffff",
        "titan": "#005fffff",
        "TWC": "#005bffff",
        "meteored": "#fd8788ff",
        "nextrad_lvl_iii": "#0726a4ff",
        "rainbow_si": "#005bffff",
        "dark_sky": "#0055ffff"
    },
    {
        "dBZ": "59",
        "black_and_white": "#dbdbdbff",
        "original": "#005fffff",
        "universal_blue": "#003fffff",
        "titan": "#005fffff",
        "TWC": "#0056ffff",
        "meteored": "#fd8788ff",
        "nextrad_lvl_iii": "#0726a4ff",
        "rainbow_si": "#0056ffff",
        "dark_sky": "#0052ffff"
    },
    {
        "dBZ": "60",
        "black_and_white": "#dcdcdcff",
        "original": "#004fffff",
        "universal_blue": "#002fffff",
        "titan": "#004fffff",
        "TWC": "#004fffff",
        "meteored": "#e90000ff",
        "nextrad_lvl_iii": "#031875ff",
        "rainbow_si": "#004fffff",
        "dark_sky": "#004fffff"
    },
    {
        "dBZ": "61",
        "black_and_white": "#ddddddff",
        "original": "#004fffff",
        "universal_blue": "#002fffff",
        "titan": "#004fffff",
        "TWC": "#004effff",
        "meteored": "#e90000ff",
        "nextrad_lvl_iii": "#031875ff",
        "rainbow_si": "#004effff",
        "dark_sky": "#004bffff"
    },
    {
        "dBZ": "62",
        "black_and_white": "#dededeff",
        "original": "#004fffff",
        "universal_blue": "#002fffff",
        "titan": "#004fffff",
        "TWC": "#004dffff",
        "meteored": "#e90000ff",
        "nextrad_lvl_iii": "#031875ff",
        "rainbow_si": "#004dffff",
        "dark_sky": "#0048ffff"
    },
    {
        "dBZ": "63",
        "black_and_white": "#dfdfdfff",
        "original": "#004fffff",
        "universal_blue": "#002fffff",
        "titan": "#004fffff",
        "TWC": "#004bffff",
        "meteored": "#e90000ff",
        "nextrad_lvl_iii": "#031875ff",
        "rainbow_si": "#004bffff",
        "dark_sky": "#0045ffff"
    },
    {
        "dBZ": "64",
        "black_and_white": "#e0e0e0ff",
        "original": "#004fffff",
        "universal_blue": "#002fffff",
        "titan": "#004fffff",
        "TWC": "#0046ffff",
        "meteored": "#e90000ff",
        "nextrad_lvl_iii": "#031875ff",
        "rainbow_si": "#0046ffff",
        "dark_sky": "#0042ffff"
    },
    {
        "dBZ": "65",
        "black_and_white": "#e1e1e1ff",
        "original": "#003fffff",
        "universal_blue": "#001fffff",
        "titan": "#003fffff",
        "TWC": "#003fffff",
        "meteored": "#a80000ff",
        "nextrad_lvl_iii": "#031875ff",
        "rainbow_si": "#003fffff",
        "dark_sky": "#003fffff"
    },
    {
        "dBZ": "66",
        "black_and_white": "#e2e2e2ff",
        "original": "#003fffff",
        "universal_blue": "#001fffff",
        "titan": "#003fffff",
        "TWC": "#003effff",
        "meteored": "#a80000ff",
        "nextrad_lvl_iii": "#031875ff",
        "rainbow_si": "#003effff",
        "dark_sky": "#003bffff"
    },
    {
        "dBZ": "67",
        "black_and_white": "#e3e3e3ff",
        "original": "#003fffff",
        "universal_blue": "#001fffff",
        "titan": "#003fffff",
        "TWC": "#003dffff",
        "meteored": "#a80000ff",
        "nextrad_lvl_iii": "#031875ff",
        "rainbow_si": "#003dffff",
        "dark_sky": "#0038ffff"
    },
    {
        "dBZ": "68",
        "black_and_white": "#e4e4e4ff",
        "original": "#003fffff",
        "universal_blue": "#001fffff",
        "titan": "#003fffff",
        "TWC": "#003bffff",
        "meteored": "#a80000ff",
        "nextrad_lvl_iii": "#031875ff",
        "rainbow_si": "#003bffff",
        "dark_sky": "#0035ffff"
    },
    {
        "dBZ": "69",
        "black_and_white": "#e5e5e5ff",
        "original": "#003fffff",
        "universal_blue": "#001fffff",
        "titan": "#003fffff",
        "TWC": "#0036ffff",
        "meteored": "#a80000ff",
        "nextrad_lvl_iii": "#031875ff",
        "rainbow_si": "#0036ffff",
        "dark_sky": "#0032ffff"
    },
    {
        "dBZ": "70",
        "black_and_white": "#e6e6e6ff",
        "original": "#002fffff",
        "universal_blue": "#000fffff",
        "titan": "#002fffff",
        "TWC": "#002fffff",
        "meteored": "#ef5beeff",
        "nextrad_lvl_iii": "#010940ff",
        "rainbow_si": "#002fffff",
        "dark_sky": "#002fffff"
    },
    {
        "dBZ": "71",
        "black_and_white": "#e7e7e7ff",
        "original": "#002fffff",
        "universal_blue": "#000fffff",
        "titan": "#002fffff",
        "TWC": "#002effff",
        "meteored": "#ef5beeff",
        "nextrad_lvl_iii": "#010940ff",
        "rainbow_si": "#002effff",
        "dark_sky": "#002bffff"
    },
    {
        "dBZ": "72",
        "black_and_white": "#e8e8e8ff",
        "original": "#002fffff",
        "universal_blue": "#000fffff",
        "titan": "#002fffff",
        "TWC": "#002dffff",
        "meteored": "#ef5beeff",
        "nextrad_lvl_iii": "#010940ff",
        "rainbow_si": "#002dffff",
        "dark_sky": "#0028ffff"
    },
    {
        "dBZ": "73",
        "black_and_white": "#e9e9e9ff",
        "original": "#002fffff",
        "universal_blue": "#000fffff",
        "titan": "#002fffff",
        "TWC": "#002bffff",
        "meteored": "#ef5beeff",
        "nextrad_lvl_iii": "#010940ff",
        "rainbow_si": "#002bffff",
        "dark_sky": "#0025ffff"
    },
    {
        "dBZ": "74",
        "black_and_white": "#eaeaeaff",
        "original": "#002fffff",
        "universal_blue": "#000fffff",
        "titan": "#002fffff",
        "TWC": "#0026ffff",
        "meteored": "#ef5beeff",
        "nextrad_lvl_iii": "#010940ff",
        "rainbow_si": "#0026ffff",
        "dark_sky": "#0022ffff"
    },
    {
        "dBZ": "75",
        "black_and_white": "#ebebebff",
        "original": "#001fffff",
        "universal_blue": "#0000ffff",
        "titan": "#001fffff",
        "TWC": "#001fffff",
        "meteored": "#924cbeff",
        "nextrad_lvl_iii": "#010940ff",
        "rainbow_si": "#001fffff",
        "dark_sky": "#001fffff"
    },
    {
        "dBZ": "76",
        "black_and_white": "#ecececff",
        "original": "#001fffff",
        "universal_blue": "#0000ffff",
        "titan": "#001fffff",
        "TWC": "#001effff",
        "meteored": "#924cbeff",
        "nextrad_lvl_iii": "#010940ff",
        "rainbow_si": "#001effff",
        "dark_sky": "#001bffff"
    },
    {
        "dBZ": "77",
        "black_and_white": "#edededff",
        "original": "#001fffff",
        "universal_blue": "#0000ffff",
        "titan": "#001fffff",
        "TWC": "#001dffff",
        "meteored": "#924cbeff",
        "nextrad_lvl_iii": "#010940ff",
        "rainbow_si": "#001dffff",
        "dark_sky": "#0018ffff"
    },
    {
        "dBZ": "78",
        "black_and_white": "#eeeeeeff",
        "original": "#001fffff",
        "universal_blue": "#0000ffff",
        "titan": "#001fffff",
        "TWC": "#001bffff",
        "meteored": "#924cbeff",
        "nextrad_lvl_iii": "#010940ff",
        "rainbow_si": "#001bffff",
        "dark_sky": "#0015ffff"
    },
    {
        "dBZ": "79",
        "black_and_white": "#efefefff",
        "original": "#001fffff",
        "universal_blue": "#0000ffff",
        "titan": "#001fffff",
        "TWC": "#0016ffff",
        "meteored": "#924cbeff",
        "nextrad_lvl_iii": "#010940ff",
        "rainbow_si": "#0016ffff",
        "dark_sky": "#0012ffff"
    },
    {
        "dBZ": "80",
        "black_and_white": "#f0f0f0ff",
        "original": "#000fffff",
        "universal_blue": "#0000ffff",
        "titan": "#000fffff",
        "TWC": "#000fffff",
        "meteored": "#502a68ff",
        "nextrad_lvl_iii": "#010940ff",
        "rainbow_si": "#000fffff",
        "dark_sky": "#000fffff"
    },
    {
        "dBZ": "81",
        "black_and_white": "#f1f1f1ff",
        "original": "#000fffff",
        "universal_blue": "#0000ffff",
        "titan": "#000fffff",
        "TWC": "#000fffff",
        "meteored": "#502a68ff",
        "nextrad_lvl_iii": "#010940ff",
        "rainbow_si": "#000fffff",
        "dark_sky": "#000fffff"
    },
    {
        "dBZ": "82",
        "black_and_white": "#f2f2f2ff",
        "original": "#000fffff",
        "universal_blue": "#0000ffff",
        "titan": "#000fffff",
        "TWC": "#000fffff",
        "meteored": "#502a68ff",
        "nextrad_lvl_iii": "#010940ff",
        "rainbow_si": "#000fffff",
        "dark_sky": "#000fffff"
    },
    {
        "dBZ": "83",
        "black_and_white": "#f3f3f3ff",
        "original": "#000fffff",
        "universal_blue": "#0000ffff",
        "titan": "#000fffff",
        "TWC": "#000fffff",
        "meteored": "#502a68ff",
        "nextrad_lvl_iii": "#010940ff",
        "rainbow_si": "#000fffff",
        "dark_sky": "#000fffff"
    },
    {
        "dBZ": "84",
        "black_and_white": "#f4f4f4ff",
        "original": "#000fffff",
        "universal_blue": "#0000ffff",
        "titan": "#000fffff",
        "TWC": "#000fffff",
        "meteored": "#502a68ff",
        "nextrad_lvl_iii": "#010940ff",
        "rainbow_si": "#000fffff",
        "dark_sky": "#000fffff"
    },
    {
        "dBZ": "85",
        "black_and_white": "#f5f5f5ff",
        "original": "#000fffff",
        "universal_blue": "#0000ffff",
        "titan": "#000fffff",
        "TWC": "#000fffff",
        "meteored": "#502a68ff",
        "nextrad_lvl_iii": "#010940ff",
        "rainbow_si": "#000fffff",
        "dark_sky": "#000fffff"
    },
    {
        "dBZ": "86",
        "black_and_white": "#f6f6f6ff",
        "original": "#000fffff",
        "universal_blue": "#0000ffff",
        "titan": "#000fffff",
        "TWC": "#000fffff",
        "meteored": "#502a68ff",
        "nextrad_lvl_iii": "#010940ff",
        "rainbow_si": "#000fffff",
        "dark_sky": "#000fffff"
    },
    {
        "dBZ": "87",
        "black_and_white": "#f7f7f7ff",
        "original": "#000fffff",
        "universal_blue": "#0000ffff",
        "titan": "#000fffff",
        "TWC": "#000fffff",
        "meteored": "#502a68ff",
        "nextrad_lvl_iii": "#010940ff",
        "rainbow_si": "#000fffff",
        "dark_sky": "#000fffff"
    },
    {
        "dBZ": "88",
        "black_and_white": "#f8f8f8ff",
        "original": "#000fffff",
        "universal_blue": "#0000ffff",
        "titan": "#000fffff",
        "TWC": "#000fffff",
        "meteored": "#502a68ff",
        "nextrad_lvl_iii": "#010940ff",
        "rainbow_si": "#000fffff",
        "dark_sky": "#000fffff"
    },
    {
        "dBZ": "89",
        "black_and_white": "#f9f9f9ff",
        "original": "#000fffff",
        "universal_blue": "#0000ffff",
        "titan": "#000fffff",
        "TWC": "#000fffff",
        "meteored": "#502a68ff",
        "nextrad_lvl_iii": "#010940ff",
        "rainbow_si": "#000fffff",
        "dark_sky": "#000fffff"
    },
    {
        "dBZ": "90",
        "black_and_white": "#fafafaff",
        "original": "#000fffff",
        "universal_blue": "#0000ffff",
        "titan": "#000fffff",
        "TWC": "#000fffff",
        "meteored": "#502a68ff",
        "nextrad_lvl_iii": "#010940ff",
        "rainbow_si": "#000fffff",
        "dark_sky": "#000fffff"
    },
    {
        "dBZ": "91",
        "black_and_white": "#fbfbfbff",
        "original": "#000fffff",
        "universal_blue": "#0000ffff",
        "titan": "#000fffff",
        "TWC": "#000fffff",
        "meteored": "#502a68ff",
        "nextrad_lvl_iii": "#010940ff",
        "rainbow_si": "#000fffff",
        "dark_sky": "#000fffff"
    },
    {
        "dBZ": "92",
        "black_and_white": "#fcfcfcff",
        "original": "#000fffff",
        "universal_blue": "#0000ffff",
        "titan": "#000fffff",
        "TWC": "#000fffff",
        "meteored": "#502a68ff",
        "nextrad_lvl_iii": "#010940ff",
        "rainbow_si": "#000fffff",
        "dark_sky": "#000fffff"
    },
    {
        "dBZ": "93",
        "black_and_white": "#fdfdfdff",
        "original": "#000fffff",
        "universal_blue": "#0000ffff",
        "titan": "#000fffff",
        "TWC": "#000fffff",
        "meteored": "#502a68ff",
        "nextrad_lvl_iii": "#010940ff",
        "rainbow_si": "#000fffff",
        "dark_sky": "#000fffff"
    },
    {
        "dBZ": "94",
        "black_and_white": "#fefefeff",
        "original": "#000fffff",
        "universal_blue": "#0000ffff",
        "titan": "#000fffff",
        "TWC": "#000fffff",
        "meteored": "#502a68ff",
        "nextrad_lvl_iii": "#010940ff",
        "rainbow_si": "#000fffff",
        "dark_sky": "#000fffff"
    },
    {
        "dBZ": "95",
        "black_and_white": "#ffffffff",
        "original": "#000fffff",
        "universal_blue": "#000fffff",
        "titan": "#000fffff",
        "TWC": "#000fffff",
        "meteored": "#502a68ff",
        "nextrad_lvl_iii": "#010940ff",
        "rainbow_si": "#000fffff",
        "dark_sky": "#000fffff"
    }
]